Workbook

Sheet Total Recap Hours
A3: Employee # | B3: Employee Name | C3: STATUS | D3: Position | E3: Social Security | F3: Address Line 1 + Address Line 2 | G3: City, State Zip Code (Formatted) | H3: Phone Number | I3: DOB | J3: DOH | K3: Hours | L3: Total
A4: 100029581 | B4: Acosta, Vilma E. | C4: Active | D4: Dishwasher | E4: 710-94-5604 | F4: 153 w 71 st | G4: Los Angeles, CA 90003 | H4: (213) 446-4417 | I4: 26170 | J4: 43182 | K4: =SUMIF(Data!$C$6:$V$29146,A4,Data!$V$6:$V$29146) -> 96.84 | L4: =IFERROR(K4*0.25,"") -> 24.21
A5: 100090935 | B5: Adamashvili, Nik | C5: Active | D5: Lead Bartender, Concess | E5: 292-99-5284 | F5: 15136 Magnolia Blvd | G5: Sherman Oaks, CA 91403 | H5: (213) 335-0335 | I5: 34974 | J5: 45736 | K5: =SUMIF(Data!$C$6:$V$29146,A5,Data!$V$6:$V$29146) -> 0 | L5: =IFERROR(K5*0.25,"") -> 0
A6: 100082265 | B6: Addison, Richard | C6: Active | D6: Concession Stand Worker | E6: 610-59-5928 | F6: 5153 S Victoria Ave | G6: Los Angeles, CA 90043 | H6: (213) 820-2054 | I6: 30930 | J6: 45414 | K6: =SUMIF(Data!$C$6:$V$29146,A6,Data!$V$6:$V$29146) -> 0 | L6: =IFERROR(K6*0.25,"") -> 0
A7: 100089151 | B7: Adkins Sr., Christopher M. | C7: Active | D7: Club Attendant | E7: 612-92-8587 | F7: 2440 East 112thplace | G7: Los Angeles, CA 90059 | H7: (213) 779-8809 | I7: 35316 | J7: 45688 | K7: =SUMIF(Data!$C$6:$V$29146,A7,Data!$V$6:$V$29146) -> 0 | L7: =IFERROR(K7*0.25,"") -> 0
A8: 100087239 | B8: Aguilar, Caesar | C8: Active | D8: Lead Bartender, Concess | E8: 616-84-1189 | F8: 6929 Coldwater Canyon Ave Apt 107 | G8: North Hollywood, CA 91605 | H8: (818) 599-4140 | I8: 34964 | J8: 45546 | K8: =SUMIF(Data!$C$6:$V$29146,A8,Data!$V$6:$V$29146) -> 0 | L8: =IFERROR(K8*0.25,"") -> 0
A9: 100082259 | B9: Aguilera, Kevin | C9: Active | D9: Dishwasher | E9: 608-80-8895 | F9: 9706 San Miguel Ave | G9: South Gate, CA 90280 | H9: (323) 775-3036 | I9: 33551 | J9: 45414 | K9: =SUMIF(Data!$C$6:$V$29146,A9,Data!$V$6:$V$29146) -> 0 | L9: =IFERROR(K9*0.25,"") -> 0
A10: 100087281 | B10: AGUILERA, MARCOS | C10: Active | D10: Cook 3 | E10: 605-90-0984 | F10: 450 s Normandie Ave Apt 109 | G10: Los Angeles, CA 90020 | H10: (323) 500-3392 | I10: 34967 | J10: 45546 | K10: =SUMIF(Data!$C$6:$V$29146,A10,Data!$V$6:$V$29146) -> 0 | L10: =IFERROR(K10*0.25,"") -> 0
A11: 100004749 | B11: Aguirre, Harold W. | C11: Active | D11: Lead Bartender, Concess | E11: 604-60-9937 | F11: 613 W Wardlow Rd | G11: Long Beach, CA 90806 | H11: (562) 761-4202 | I11: 28294 | J11: 45688 | K11: =SUMIF(Data!$C$6:$V$29146,A11,Data!$V$6:$V$29146) -> 0 | L11: =IFERROR(K11*0.25,"") -> 0
A12: 100062550 | B12: Albitre, Randy | C12: Active | D12: Concession Stand Worker | E12: 558-67-5709 | F12: 526 E.6th St. Unit 304 | G12: Los Angeles, CA 90021 | H12: (323) 571-0693 | I12: 29757 | J12: 44832 | K12: =SUMIF(Data!$C$6:$V$29146,A12,Data!$V$6:$V$29146) -> 0 | L12: =IFERROR(K12*0.25,"") -> 0
A13: 100064555 | B13: ALCAZAR, LOUIE A. | C13: Active | D13: Concession Stand Worker | E13: 624-11-2408 | F13: 4172 wall st | G13: Los Angeles, CA 90011 | H13: (323) 812-8635 | I13: 36222 | J13: 44958 | K13: =SUMIF(Data!$C$6:$V$29146,A13,Data!$V$6:$V$29146) -> 0 | L13: =IFERROR(K13*0.25,"") -> 0
A14: 100093400 | B14: Aleman, Amelia | C14: Active | D14: Cook 3 | E14: 623-44-4835 | F14: 12223 Atlantic Ave Unit 1305 | G14: Lynwood, CA 90262 | H14: (323) 273-7429 | I14: 26200 | J14: 45785 | K14: =SUMIF(Data!$C$6:$V$29146,A14,Data!$V$6:$V$29146) -> 0 | L14: =IFERROR(K14*0.25,"") -> 0
A15: 100094450 | B15: Aleman, Fransico | C15: Active | D15: Dishwasher | E15: 613-17-1565 | F15: 435 e 105th st | G15: Los angeles, CA 90003 | H15: (323) 994-7216 | I15: 36436 | J15: 45805 | K15: =SUMIF(Data!$C$6:$V$29146,A15,Data!$V$6:$V$29146) -> 0 | L15: =IFERROR(K15*0.25,"") -> 0
A16: 100087249 | B16: Allen, Yeshayahuw | C16: Active | D16: Cashier, Concessions | E16: 606-35-4445 | F16: 1947 W 39th Pl Van Ness Avenue | G16: Los Angeles, CA 90062 | H16: (323) 217-8663 | I16: 37460 | J16: 45546 | K16: =SUMIF(Data!$C$6:$V$29146,A16,Data!$V$6:$V$29146) -> 0 | L16: =IFERROR(K16*0.25,"") -> 0
A17: 100071939 | B17: Alonso, Jose | C17: Active | D17: Cook 3 | E17: 626-47-1926 | F17: 514 S Westlake Ave, Apt 107 | G17: Los Angeles, CA 90057 | H17: (213) 705-9380 | I17: 38282 | J17: 45112 | K17: =SUMIF(Data!$C$6:$V$29146,A17,Data!$V$6:$V$29146) -> 0 | L17: =IFERROR(K17*0.25,"") -> 0
A18: 100087236 | B18: ALVARADO, FREDY | C18: Active | D18: Cook 3 | E18: 626-55-1785 | F18: 5334 Oakland St | G18: Los Angeles, CA 90032 | H18: (323) 714-7509 | I18: 38767 | J18: 45546 | K18: =SUMIF(Data!$C$6:$V$29146,A18,Data!$V$6:$V$29146) -> 0 | L18: =IFERROR(K18*0.25,"") -> 0
A19: 100029801 | B19: Alvarado, Leticia | C19: Active | D19: Bartender, Premium | E19: 553-33-8803 | F19: 10855 Terra Vista Pkwy Apt 126 | G19: Rancho Cucamonga, CA 91730 | H19: (626) 260-2506 | I19: 25507 | J19: 43182 | K19: =SUMIF(Data!$C$6:$V$29146,A19,Data!$V$6:$V$29146) -> 6.67 | L19: =IFERROR(K19*0.25,"") -> 1.6675
A20: 100087241 | B20: ALVAREZ, LUIS F. | C20: Active | D20: Cashier, Concessions | E20: 608-59-1294 | F20: 629 w 43rd st | G20: Los angeles, CA 90037 | H20: (424) 404-2342 | I20: 38925 | J20: 45546 | K20: =SUMIF(Data!$C$6:$V$29146,A20,Data!$V$6:$V$29146) -> 0 | L20: =IFERROR(K20*0.25,"") -> 0
A21: 100093373 | B21: Ambrocio IV, Marco A. | C21: Active | D21: Concession Stand Worker | E21: 625-59-6704 | F21: 15348 Firmona Ave | G21: Lawndale, CA 90260 | H21: (310) 706-8049 | I21: 39009 | J21: 45785 | K21: =SUMIF(Data!$C$6:$V$29146,A21,Data!$V$6:$V$29146) -> 0 | L21: =IFERROR(K21*0.25,"") -> 0
A22: 100084221 | B22: Amigon, Judith | C22: Active | D22: Dishwasher | E22: 623-78-6472 | F22: 181 W 41st Pl Apt, 5 | G22: Los Anfgeles, CA 90037 | H22: (626) 549-7403 | I22: 25421 | J22: 45456 | K22: =SUMIF(Data!$C$6:$V$29146,A22,Data!$V$6:$V$29146) -> 0 | L22: =IFERROR(K22*0.25,"") -> 0
A23: 100089112 | B23: Anderson, Rashad | C23: Active | D23: Club Attendant | E23: 591-11-4797 | F23: 888 S Olive St Apt 3007 | G23: Los Angeles, CA 90014 | H23: (813) 796-2072 | I23: 33318 | J23: 45688 | K23: =SUMIF(Data!$C$6:$V$29146,A23,Data!$V$6:$V$29146) -> 0 | L23: =IFERROR(K23*0.25,"") -> 0
A24: 100074386 | B24: ANDON Gomez, KEVIN D. | C24: Active | D24: Runner, Suites | E24: 096-88-6401 | F24: 5914 Willowcrest Apt 1 | G24: North Hollywood, CA 91601 | H24: (818) 209-5759 | I24: 34813 | J24: 45189 | K24: =SUMIF(Data!$C$6:$V$29146,A24,Data!$V$6:$V$29146) -> 0 | L24: =IFERROR(K24*0.25,"") -> 0
A25: 100093414 | B25: Apolinar, Carlos | C25: Active | D25: Cashier, Concessions | E25: 611-31-2369 | F25: 133 E 25th St | G25: Los Angeles, CA 90011 | H25: (323) 816-5696 | I25: 37222 | J25: 45785 | K25: =SUMIF(Data!$C$6:$V$29146,A25,Data!$V$6:$V$29146) -> 0 | L25: =IFERROR(K25*0.25,"") -> 0
A26: 100082257 | B26: Apolinar, Citlali | C26: Active | D26: Concession Stand Worker | E26: 624-45-2335 | F26: 133 E 25th St | G26: Los Angeles, CA 90011 | H26: (323) 379-9899 | I26: 38147 | J26: 45414 | K26: =SUMIF(Data!$C$6:$V$29146,A26,Data!$V$6:$V$29146) -> 0 | L26: =IFERROR(K26*0.25,"") -> 0
A27: 100029855 | B27: Aquino Carrillo, Febronia J. | C27: Active | D27: Dishwasher | E27: 780-86-0496 | F27: 466 W 50TH ST | G27: Los Angeles, CA 90037 | H27: (213) 260-5668 | I27: 24649 | J27: 43182 | K27: =SUMIF(Data!$C$6:$V$29146,A27,Data!$V$6:$V$29146) -> 20.35 | L27: =IFERROR(K27*0.25,"") -> 5.0875
A28: 100084258 | B28: Arellanes, Jacob | C28: Active | D28: Concession Stand Worker | E28: 614-80-4086 | F28: 762 Via Altamira Apt 21 | G28: Montebello, CA 90640 | H28: (323) 712-5623 | I28: 31246 | J28: 45456 | K28: =SUMIF(Data!$C$6:$V$29146,A28,Data!$V$6:$V$29146) -> 0 | L28: =IFERROR(K28*0.25,"") -> 0
A29: 100089129 | B29: Arredondo, Militza | C29: Active | D29: Dishwasher | E29: 062-17-7339 | F29: 1780 E 109th Pl | G29: Los Angeles, CA 90059 | H29: (323) 635-4727 | I29: 34572 | J29: 45688 | K29: =SUMIF(Data!$C$6:$V$29146,A29,Data!$V$6:$V$29146) -> 0 | L29: =IFERROR(K29*0.25,"") -> 0
A30: 100087283 | B30: Arteaga, Juan A. | C30: Active | D30: Runner, Suites | E30: 621-78-4344 | F30: 10603 Felton ave | G30: Lennox, CA 90304 | H30: (213) 844-1561 | I30: 34452 | J30: 45546 | K30: =SUMIF(Data!$C$6:$V$29146,A30,Data!$V$6:$V$29146) -> 0 | L30: =IFERROR(K30*0.25,"") -> 0
A31: 100059503 | B31: ARTIGA, RODOLFO | C31: Active | D31: Dishwasher | E31: 624-46-5343 | F31: 429 S.Rampart blvd apt2 | G31: los angeles, CA 90057 | H31: (213) 247-4463 | I31: 21292 | J31: 44735 | K31: =SUMIF(Data!$C$6:$V$29146,A31,Data!$V$6:$V$29146) -> 0 | L31: =IFERROR(K31*0.25,"") -> 0
A32: 100040078 | B32: ATKINS, SASHA | C32: Active | D32: Suite Attendant | E32: 608-28-2754 | F32: 4575 Ramona Ave 1 | G32: La Verne, CA 91750 | H32: (562) 205-7829 | I32: 32666 | J32: 43628 | K32: =SUMIF(Data!$C$6:$V$29146,A32,Data!$V$6:$V$29146) -> 0 | L32: =IFERROR(K32*0.25,"") -> 0
A33: 100089134 | B33: Avalos, Gabriela C. | C33: Active | D33: Dishwasher | E33: 833-07-5886 | F33: 10413 S Gravillea Ave | G33: Inglewood, CA 90304 | H33: (424) 393-8674 | I33: 23427 | J33: 45688 | K33: =SUMIF(Data!$C$6:$V$29146,A33,Data!$V$6:$V$29146) -> 0 | L33: =IFERROR(K33*0.25,"") -> 0
A34: 100093395 | B34: Avelar, Yovani | C34: Active | D34: Cashier, Concessions | E34: 624-98-2754 | F34: 1599 E 45th st Apt 3 | G34: Los Angeles, CA 90011 | I34: 35308 | J34: 45785 | K34: =SUMIF(Data!$C$6:$V$29146,A34,Data!$V$6:$V$29146) -> 0 | L34: =IFERROR(K34*0.25,"") -> 0
A35: 100093374 | B35: Avila, Francisco | C35: Active | D35: Cashier, Concessions | E35: 612-55-7694 | F35: 11507 S New Hampshire Ave | G35: Los Angeles, CA 90044 | H35: (323) 326-2496 | I35: 38704 | J35: 45785 | K35: =SUMIF(Data!$C$6:$V$29146,A35,Data!$V$6:$V$29146) -> 0 | L35: =IFERROR(K35*0.25,"") -> 0
A36: 100087267 | B36: Bachez, Elba | C36: Active | D36: Dishwasher | E36: 085-87-9317 | F36: 2222 S FIGUEROA ST PH25 | G36: LOS ANGELES, CA 90007 | H36: (323) 789-9181 | I36: 23735 | J36: 45546 | K36: =SUMIF(Data!$C$6:$V$29146,A36,Data!$V$6:$V$29146) -> 0 | L36: =IFERROR(K36*0.25,"") -> 0
A37: 100084254 | B37: Bailon, Denisse M. | C37: Active | D37: Cook 2 | E37: 729-14-9013 | F37: 1514 West 46 Street 1/2 | G37: Los Angeles, CA 90062 | H37: (323) 694-8834 | I37: 32599 | J37: 45456 | K37: =SUMIF(Data!$C$6:$V$29146,A37,Data!$V$6:$V$29146) -> 0 | L37: =IFERROR(K37*0.25,"") -> 0
A38: 100013984 | B38: Bailon, Maria | C38: Active | D38: Lead Bartender, Concess | E38: 551-99-3124 | F38: 3951 HALLDALE AVE. | G38: Los Angeles, CA 90062 | H38: (213) 220-0714 | I38: 24353 | J38: 42270 | K38: =SUMIF(Data!$C$6:$V$29146,A38,Data!$V$6:$V$29146) -> 0 | L38: =IFERROR(K38*0.25,"") -> 0
A39: 100084236 | B39: Baker, Aniyah | C39: Active | D39: Cashier, Concessions | E39: 760-01-7557 | F39: 1205 W 65th Pl | G39: Los Angeles, CA 90044 | H39: (539) 281-9291 | I39: 38645 | J39: 45456 | K39: =SUMIF(Data!$C$6:$V$29146,A39,Data!$V$6:$V$29146) -> 0 | L39: =IFERROR(K39*0.25,"") -> 0
A40: 100037610 | B40: BAKER, TYNASIA L. | C40: Active | D40: Concessions Stand Lead | E40: 610-84-2914 | F40: 3016 w 82nd Street | G40: Inglewood, CA 90305 | H40: (323) 674-4900 | I40: 34934 | J40: 45546 | K40: =SUMIF(Data!$C$6:$V$29146,A40,Data!$V$6:$V$29146) -> 0 | L40: =IFERROR(K40*0.25,"") -> 0
A41: 100064799 | B41: BALBUENA, YOLANDA | C41: Active | D41: Cook 2 | E41: 353-65-4445 | F41: 4212 s. Grand ave | G41: LOS ANGELES, CA 90037 | H41: (323) 697-1187 | I41: 26972 | J41: 44965 | K41: =SUMIF(Data!$C$6:$V$29146,A41,Data!$V$6:$V$29146) -> 0 | L41: =IFERROR(K41*0.25,"") -> 0
A42: 100082245 | B42: Barnes, Darrionna | C42: Active | D42: In-Seat Server | E42: 346-90-4314 | F42: 752 S Main St 452 | G42: Los Angeles, CA 90014 | H42: (773) 541-0977 | I42: 34635 | J42: 45414 | K42: =SUMIF(Data!$C$6:$V$29146,A42,Data!$V$6:$V$29146) -> 0 | L42: =IFERROR(K42*0.25,"") -> 0
A43: 100054457 | B43: BARNES, LEANNA M. | C43: Active | D43: Bartender, Premium | E43: 555-93-9385 | F43: 5550 Hollywood Blvd Apt 304 | G43: Los Angeles, CA 90028 | H43: (323) 286-1258 | I43: 31752 | J43: 44612 | K43: =SUMIF(Data!$C$6:$V$29146,A43,Data!$V$6:$V$29146) -> 0 | L43: =IFERROR(K43*0.25,"") -> 0
A44: 13429 | B44: Beltran, Karina S. | C44: Active | D44: Suite Attendant | E44: 602-60-5876 | F44: 734 Camphor Way | G44: Upland, CA 91786 | H44: (156) 280-5579 | I44: 33861 | J44: 41507 | K44: =SUMIF(Data!$C$6:$V$29146,A44,Data!$V$6:$V$29146) -> 0 | L44: =IFERROR(K44*0.25,"") -> 0
A45: 100029842 | B45: Benitez, Grisela B. | C45: Active | D45: Cook 2 | E45: 614-87-7938 | F45: 614 W. 50th St. | G45: Los Angeles, CA 90037 | H45: (323) 671-8648 | I45: 29401 | J45: 43182 | K45: =SUMIF(Data!$C$6:$V$29146,A45,Data!$V$6:$V$29146) -> 0 | L45: =IFERROR(K45*0.25,"") -> 0
A46: 100093434 | B46: Bernstine, Royalle J. | C46: Active | D46: Cook 3 | E46: 631-56-7062 | F46: 2233 e 69th Street | G46: Long Beach, CA 90805 | H46: (562) 721-7450 | I46: 35477 | J46: 45785 | K46: =SUMIF(Data!$C$6:$V$29146,A46,Data!$V$6:$V$29146) -> 0 | L46: =IFERROR(K46*0.25,"") -> 0
A47: 100090863 | B47: Bisaha, Mark | C47: Active | D47: Club Attendant | E47: 572-96-9800 | F47: 5420 Russell Avenue Apt 8 | G47: Los Angeles, CA 90027 | H47: (213) 221-7416 | I47: 23275 | J47: 45736 | K47: =SUMIF(Data!$C$6:$V$29146,A47,Data!$V$6:$V$29146) -> 0 | L47: =IFERROR(K47*0.25,"") -> 0
A48: 100059597 | B48: BLACK, LASONYA | C48: Active | D48: Cashier, Concessions | E48: 559-49-7692 | F48: 331 Daisy Ave | G48: Long Beach, CA 90802 | H48: (323) 691-5352 | I48: 27477 | J48: 44735 | K48: =SUMIF(Data!$C$6:$V$29146,A48,Data!$V$6:$V$29146) -> 0 | L48: =IFERROR(K48*0.25,"") -> 0
A49: 100064557 | B49: BLACKWOOD, JADA K. | C49: Active | D49: Barback, Premium | E49: 604-19-6853 | F49: 2303 Grandeur Ave | G49: Altadena, CA 91001 | H49: (213) 434-6206 | I49: 36581 | J49: 44958 | K49: =SUMIF(Data!$C$6:$V$29146,A49,Data!$V$6:$V$29146) -> 0 | L49: =IFERROR(K49*0.25,"") -> 0
A50: 100093389 | B50: Boone, Rachel | C50: Active | D50: Club Attendant | E50: 329-48-4240 | F50: 510 Centinela Avenue Apt. 205 | G50: Inglewood, CA 90302 | H50: (310) 345-6933 | I50: 19112 | J50: 45785 | K50: =SUMIF(Data!$C$6:$V$29146,A50,Data!$V$6:$V$29146) -> 0 | L50: =IFERROR(K50*0.25,"") -> 0
A51: 100044773 | B51: Boren, Adam | C51: Active | D51: Server, Catering | E51: 568-59-5885 | F51: 10155 brockway st | G51: SOUTH EL MONTE, CA 91733 | H51: (626) 216-8518 | I51: 29257 | J51: 43886 | K51: =SUMIF(Data!$C$6:$V$29146,A51,Data!$V$6:$V$29146) -> 7.88 | L51: =IFERROR(K51*0.25,"") -> 1.97
A52: 100087224 | B52: BORQUEZ, NATHAN | C52: Active | D52: Concessions Stand Lead | E52: 619-43-3593 | F52: 2814 Walnut St | G52: Huntington Park, CA 90255 | H52: (323) 440-7511 | I52: 37976 | J52: 45546 | K52: =SUMIF(Data!$C$6:$V$29146,A52,Data!$V$6:$V$29146) -> 0 | L52: =IFERROR(K52*0.25,"") -> 0
A53: 100089121 | B53: Branch, Rita | C53: Active | D53: Club Attendant | E53: 566-49-7242 | F53: 1323 W. 82nd St. | G53: Los Angeles, CA 90045 | H53: (323) 697-6163 | I53: 23434 | J53: 45688 | K53: =SUMIF(Data!$C$6:$V$29146,A53,Data!$V$6:$V$29146) -> 0 | L53: =IFERROR(K53*0.25,"") -> 0
A54: 100036214 | B54: Brantley, Kenneth L. | C54: Active | D54: Concession Stand Worker | E54: 545-33-0746 | F54: 1069 Browning Blvd. #5 | G54: LOS ANGELES, CA 90037 | H54: (626) 525-3251 | I54: 21967 | J54: 43503 | K54: =SUMIF(Data!$C$6:$V$29146,A54,Data!$V$6:$V$29146) -> 0 | L54: =IFERROR(K54*0.25,"") -> 0
A55: 100071821 | B55: Bravo, Fernando | C55: Active | D55: Cook 3 | E55: 605-41-8022 | F55: 748 E 43rd St | G55: Los Angeles, CA 90011 | H55: (323) 678-8290 | I55: 37781 | J55: 45112 | K55: =SUMIF(Data!$C$6:$V$29146,A55,Data!$V$6:$V$29146) -> 0 | L55: =IFERROR(K55*0.25,"") -> 0
A56: 100084255 | B56: Bravo, Gabriela | C56: Active | D56: Concession Stand Worker | E56: 616-20-6904 | F56: 762 Via Altamira apt.21 | G56: Montebello, CA 90640 | H56: (323) 360-2977 | I56: 32381 | J56: 45456 | K56: =SUMIF(Data!$C$6:$V$29146,A56,Data!$V$6:$V$29146) -> 0 | L56: =IFERROR(K56*0.25,"") -> 0
A57: 100032210 | B57: Brito, Mario R. | C57: Active | D57: Warehouse Associate | E57: 603-60-4601 | F57: 232 W 49th St | G57: Los Angeles, CA 90037 | H57: (213) 298-7039 | I57: 33857 | J57: 43237 | K57: =SUMIF(Data!$C$6:$V$29146,A57,Data!$V$6:$V$29146) -> 0 | L57: =IFERROR(K57*0.25,"") -> 0
A58: 100089142 | B58: Brown, Eric J. | C58: Active | D58: Club Attendant | E58: 622-35-4628 | F58: 957 1/2 west 42nd street | G58: Los Angeles, CA 90037 | H58: (323) 631-7550 | I58: 37521 | J58: 45688 | K58: =SUMIF(Data!$C$6:$V$29146,A58,Data!$V$6:$V$29146) -> 7.97 | L58: =IFERROR(K58*0.25,"") -> 1.9925
A59: 100087245 | B59: BROWN, NICHOLAS | C59: Active | D59: Cashier, Concessions | E59: 612-23-8959 | F59: 762 W 99th St | G59: Los Angeles, CA 90044 | H59: (213) 400-6838 | I59: 36885 | J59: 45546 | K59: =SUMIF(Data!$C$6:$V$29146,A59,Data!$V$6:$V$29146) -> 0 | L59: =IFERROR(K59*0.25,"") -> 0
A60: 100093411 | B60: Bruton, Diamond | C60: Active | D60: Cashier, Concessions | E60: 274-98-4416 | F60: 1037 W 85th St | G60: Los Angeles, CA 90044 | I60: 34561 | J60: 45785 | K60: =SUMIF(Data!$C$6:$V$29146,A60,Data!$V$6:$V$29146) -> 0 | L60: =IFERROR(K60*0.25,"") -> 0
A61: 100093387 | B61: Burman III, Darryl | C61: Active | D61: Cook 3 | E61: 617-33-6506 | F61: 7827 S Normandie Ave | G61: Los Angeles, CA 90044 | H61: (562) 302-3737 | I61: 37423 | J61: 45785 | K61: =SUMIF(Data!$C$6:$V$29146,A61,Data!$V$6:$V$29146) -> 8.1 | L61: =IFERROR(K61*0.25,"") -> 2.025
A62: 100032347 | B62: BUSBEE, TAJANEE | C62: Active | D62: Concessions Stand Lead | E62: 602-06-5572 | F62: 10600 s Inglewood ave apt 21 | G62: Inglewood, CA 90304 | H62: (626) 417-4693 | I62: 35884 | J62: 43238 | K62: =SUMIF(Data!$C$6:$V$29146,A62,Data!$V$6:$V$29146) -> 0 | L62: =IFERROR(K62*0.25,"") -> 0
A63: 100089117 | B63: Cabral Jr., Edgardo | C63: Active | D63: Club Attendant | E63: 624-60-2824 | F63: 241 S. Ave 57 #122 | G63: Los Angeles, CA 90042 | H63: (323) 551-7247 | I63: 33937 | J63: 45688 | K63: =SUMIF(Data!$C$6:$V$29146,A63,Data!$V$6:$V$29146) -> 0 | L63: =IFERROR(K63*0.25,"") -> 0
A64: 100032198 | B64: CALDERA, MARISOL | C64: Active | D64: Suite Attendant | E64: 567-49-5918 | F64: 3704 e 55th st | G64: Maywood, CA 90270 | H64: (323) 517-3354 | I64: 23391 | J64: 43237 | K64: =SUMIF(Data!$C$6:$V$29146,A64,Data!$V$6:$V$29146) -> 0 | L64: =IFERROR(K64*0.25,"") -> 0
A65: 100093435 | B65: Caloca Jr., Oscar | C65: Active | D65: Cook 3 | E65: 613-53-3952 | F65: 10849 Gorman ave | G65: Los Angeles, CA 90059 | H65: (323) 425-7562 | I65: 38598 | J65: 45785 | K65: =SUMIF(Data!$C$6:$V$29146,A65,Data!$V$6:$V$29146) -> 0 | L65: =IFERROR(K65*0.25,"") -> 0
A66: 100093398 | B66: Cao, Audrey | C66: Active | D66: Club Attendant | E66: 606-53-7804 | F66: 6007 village rd | G66: Lakewood, CA 90713 | H66: (562) 515-8520 | I66: 38575 | J66: 45785 | K66: =SUMIF(Data!$C$6:$V$29146,A66,Data!$V$6:$V$29146) -> 0 | L66: =IFERROR(K66*0.25,"") -> 0
A67: 100093408 | B67: Cardenas, Bryan | C67: Active | D67: Club Attendant | E67: 606-08-9773 | F67: 581 W Blaine st | G67: Riverside, CA 92507 | H67: (951) 660-6697 | I67: 36031 | J67: 45785 | K67: =SUMIF(Data!$C$6:$V$29146,A67,Data!$V$6:$V$29146) -> 0 | L67: =IFERROR(K67*0.25,"") -> 0
A68: 100084233 | B68: Cardenas, Daniel F. | C68: Active | D68: Runner, Suites | E68: 613-57-2649 | F68: 1033 W 56th St | G68: Los Angeles, CA 90037 | H68: (323) 534-5611 | I68: 38816 | J68: 45456 | K68: =SUMIF(Data!$C$6:$V$29146,A68,Data!$V$6:$V$29146) -> 0 | L68: =IFERROR(K68*0.25,"") -> 0
A69: 100041448 | B69: Carranza, Eulogio S. | C69: Active | D69: Dishwasher | E69: 347-29-9898 | F69: 5214 Randolph St | G69: Bell, CA 90201 | H69: (323) 358-0966 | I69: 24177 | J69: 43677 | K69: =SUMIF(Data!$C$6:$V$29146,A69,Data!$V$6:$V$29146) -> 14.28 | L69: =IFERROR(K69*0.25,"") -> 3.57
A70: 100090864 | B70: Carranza, Miguel A. | C70: Active | D70: Barback, Premium | E70: 557-89-2800 | F70: 1861 Middleton | G70: Los Angeles, CA 90062 | H70: (323) 540-1387 | I70: 31499 | J70: 45736 | K70: =SUMIF(Data!$C$6:$V$29146,A70,Data!$V$6:$V$29146) -> 0 | L70: =IFERROR(K70*0.25,"") -> 0
A71: 100077552 | B71: CARRERO, NICHOLAS J. | C71: Active | D71: Barback, Premium | E71: 142-96-2053 | F71: 15700 Belshire Ave Apt.22 | G71: Norwalk, CA 90650 | H71: (562) 607-9499 | I71: 34407 | J71: 45322 | K71: =SUMIF(Data!$C$6:$V$29146,A71,Data!$V$6:$V$29146) -> 0 | L71: =IFERROR(K71*0.25,"") -> 0
A72: 100049315 | B72: CARRILLO, CHRISTIAN | C72: Active | D72: Cashier, Concessions | E72: 613-29-5652 | F72: 7300 Marbrisa Ave | G72: Huntington Park, CA 90255 | H72: (323) 354-0533 | I72: 31484 | J72: 44392 | K72: =SUMIF(Data!$C$6:$V$29146,A72,Data!$V$6:$V$29146) -> 0 | L72: =IFERROR(K72*0.25,"") -> 0
A73: 100035330 | B73: Carrillo, Juan | C73: Active | D73: Bartender, Premium | E73: 615-61-9543 | F73: 13213 Curtis and king rd | G73: Norwalk, CA 90650 | H73: (562) 320-4575 | I73: 29162 | J73: 43355 | K73: =SUMIF(Data!$C$6:$V$29146,A73,Data!$V$6:$V$29146) -> 0 | L73: =IFERROR(K73*0.25,"") -> 0
A74: 100093369 | B74: Carter, Nakika | C74: Active | D74: Cook 3 | E74: 550-43-2917 | F74: 211 Witmer st. #101 | G74: Los Angeles, CA 90026 | H74: (515) 868-9823 | I74: 27901 | J74: 45785 | K74: =SUMIF(Data!$C$6:$V$29146,A74,Data!$V$6:$V$29146) -> 0 | L74: =IFERROR(K74*0.25,"") -> 0
A75: 100032197 | B75: Carter, Samantha B. | C75: Active | D75: Suite Attendant | E75: 633-07-0557 | F75: 3306 Casitas Ave | G75: Los Angeles, CA 90039 | H75: (214) 517-6470 | I75: 32504 | J75: 43237 | K75: =SUMIF(Data!$C$6:$V$29146,A75,Data!$V$6:$V$29146) -> 0 | L75: =IFERROR(K75*0.25,"") -> 0
A76: 100067135 | B76: Cash, Paul | C76: Active | D76: Bartender, Premium | E76: 558-35-6917 | F76: 4460 Overland Ave Apt #27 | G76: Culver City, CA 90230 | H76: (310) 748-6653 | I76: 23655 | J76: 45028 | K76: =SUMIF(Data!$C$6:$V$29146,A76,Data!$V$6:$V$29146) -> 0 | L76: =IFERROR(K76*0.25,"") -> 0
A77: 100087256 | B77: CASTILLO, CARLOS A. | C77: Active | D77: Concession Stand Worker | E77: 616-57-9184 | F77: 1136 W 42nd St | G77: Los Angeles, CA 90037 | H77: (323) 774-4831 | I77: 38859 | J77: 45546 | K77: =SUMIF(Data!$C$6:$V$29146,A77,Data!$V$6:$V$29146) -> 0 | L77: =IFERROR(K77*0.25,"") -> 0
A78: 100032283 | B78: Castillo, Demica L. | C78: Active | D78: Concessions Stand Lead | E78: 547-35-9981 | F78: 1302 E 41 st apt. 404 | G78: Los angeles, CA 90011 | H78: (323) 633-7511 | I78: 24800 | J78: 43238 | K78: =SUMIF(Data!$C$6:$V$29146,A78,Data!$V$6:$V$29146) -> 6.67 | L78: =IFERROR(K78*0.25,"") -> 1.6675
A79: 100087271 | B79: Castillo, Janet | C79: Active | D79: Cook 2 | E79: 569-73-5997 | F79: 6625 Loma Vista Pl Apt.C | G79: Bell, CA 90201 | H79: (323) 239-0089 | I79: 30138 | J79: 45546 | K79: =SUMIF(Data!$C$6:$V$29146,A79,Data!$V$6:$V$29146) -> 29.53 | L79: =IFERROR(K79*0.25,"") -> 7.3825
A80: 100059824 | B80: CATALINO Montilla, FLERIDA | C80: Active | D80: Bartender, Premium | E80: 597-28-0697 | F80: PO BOX 342 | G80: North Hollywood, CA 91603 | H80: (917) 557-6027 | I80: 28281 | J80: 44742 | K80: =SUMIF(Data!$C$6:$V$29146,A80,Data!$V$6:$V$29146) -> 0 | L80: =IFERROR(K80*0.25,"") -> 0
A81: 100084220 | B81: Cerezo, Osman D. | C81: Active | D81: Concession Stand Worker | E81: 607-51-5318 | F81: 2842 E 6th Street | G81: Los Angeles, CA 90023 | H81: (323) 702-5129 | I81: 38441 | J81: 45456 | K81: =SUMIF(Data!$C$6:$V$29146,A81,Data!$V$6:$V$29146) -> 0 | L81: =IFERROR(K81*0.25,"") -> 0
A82: 100093375 | B82: Ceron Sr., Francisco J. | C82: Active | D82: Cook 3 | E82: 604-17-0363 | F82: 1184 Browning Blvd | G82: Los Angeles, CA 90037-1628 | H82: (323) 705-2307 | I82: 33290 | J82: 45785 | K82: =SUMIF(Data!$C$6:$V$29146,A82,Data!$V$6:$V$29146) -> 0 | L82: =IFERROR(K82*0.25,"") -> 0
A83: 100093441 | B83: Cervantes, Brenda L. | C83: Active | D83: Cook 1 | E83: 565-83-7889 | F83: 2806 S Hobart Blvd | G83: Los Angeles, CA 90018 | H83: (213) 318-7109 | I83: 31118 | J83: 45785 | K83: =SUMIF(Data!$C$6:$V$29146,A83,Data!$V$6:$V$29146) -> 0 | L83: =IFERROR(K83*0.25,"") -> 0
A84: 100036211 | B84: Chairez, Ricardo | C84: Active | D84: Lead Bartender, Concess | E84: 609-82-4597 | F84: 5669 Stratford Rd | G84: Los Angeles, CA 90042 | H84: (424) 394-3114 | I84: 29975 | J84: 43503 | K84: =SUMIF(Data!$C$6:$V$29146,A84,Data!$V$6:$V$29146) -> 38.74 | L84: =IFERROR(K84*0.25,"") -> 9.685
A85: 100059825 | B85: CHAPA, VICTOR | C85: Active | D85: Bartender, Premium | E85: 547-53-7065 | F85: 401 N Vail Ave | G85: Montebello, CA 90640 | H85: (323) 804-6271 | I85: 23725 | J85: 44742 | K85: =SUMIF(Data!$C$6:$V$29146,A85,Data!$V$6:$V$29146) -> 0 | L85: =IFERROR(K85*0.25,"") -> 0
A86: 100059508 | B86: CHERBONY, YVETTE D. | C86: Active | D86: Bartender, Premium | E86: 603-60-1717 | F86: 2753 Newell st | G86: Los Ángeles, CA 90039 | H86: (818) 216-1293 | I86: 25716 | J86: 44735 | K86: =SUMIF(Data!$C$6:$V$29146,A86,Data!$V$6:$V$29146) -> 6.26 | L86: =IFERROR(K86*0.25,"") -> 1.565
A87: 100064560 | B87: CHRISTOPHER, JADON R. | C87: Active | D87: Concession Stand Worker | E87: 617-21-8937 | F87: 322 Culver Boulevard #329 | G87: Playa Del Rey, CA 90293 | H87: (323) 348-3469 | I87: 36728 | J87: 44958 | K87: =SUMIF(Data!$C$6:$V$29146,A87,Data!$V$6:$V$29146) -> 0 | L87: =IFERROR(K87*0.25,"") -> 0
A88: 100074373 | B88: Christopher, Jahcai | C88: Active | D88: Cashier, Concessions | E88: 608-53-9720 | F88: 322 Culver Boulevard #329 | G88: Playa vista, CA 90293 | H88: (323) 348-3435 | I88: 38583 | J88: 45189 | K88: =SUMIF(Data!$C$6:$V$29146,A88,Data!$V$6:$V$29146) -> 0 | L88: =IFERROR(K88*0.25,"") -> 0
A89: 100074381 | B89: Christopher, jahmai | C89: Active | D89: Cashier, Concessions | E89: 608-53-9719 | F89: 322 Culver Boulevard #329 | G89: Playa Del Rey, CA 90293 | H89: (323) 348-3467 | I89: 38583 | J89: 45189 | K89: =SUMIF(Data!$C$6:$V$29146,A89,Data!$V$6:$V$29146) -> 0 | L89: =IFERROR(K89*0.25,"") -> 0
A90: 100087223 | B90: Chun, Alex | C90: Active | D90: Runner, Suites | E90: 624-25-0520 | F90: 1633 3rd Avenue | G90: Los Angeles, CA 90019 | H90: (805) 377-3916 | I90: 37013 | J90: 45546 | K90: =SUMIF(Data!$C$6:$V$29146,A90,Data!$V$6:$V$29146) -> 0 | L90: =IFERROR(K90*0.25,"") -> 0
A91: 100087217 | B91: COLEMAN-OWENS, YOLANDA | C91: Active | D91: Cashier, Concessions | E91: 545-43-3363 | F91: 5437 Virginia Ave APT 306 | G91: Los Angeles, CA 90029 | H91: (213) 678-0266 | I91: 25077 | J91: 45546 | K91: =SUMIF(Data!$C$6:$V$29146,A91,Data!$V$6:$V$29146) -> 0 | L91: =IFERROR(K91*0.25,"") -> 0
A92: 100068468 | B92: COLLAZO, ALYSSA A. | C92: Active | D92: Runner, Suites | E92: 622-43-7887 | F92: 7402 Whitsett Ave | G92: Los Angeles, CA 90001 | H92: (323) 540-1599 | I92: 37987 | J92: 45050 | K92: =SUMIF(Data!$C$6:$V$29146,A92,Data!$V$6:$V$29146) -> 0 | L92: =IFERROR(K92*0.25,"") -> 0
A93: 100030336 | B93: Collins, Spencer E. | C93: Active | D93: Suite Attendant | E93: 621-12-9303 | F93: 1642 S. Highland Ave | G93: Los Angeles, CA 90019 | H93: (323) 592-0033 | I93: 32296 | J93: 43196 | K93: =SUMIF(Data!$C$6:$V$29146,A93,Data!$V$6:$V$29146) -> 0 | L93: =IFERROR(K93*0.25,"") -> 0
A94: 100093376 | B94: Colop I, Brandi M. | C94: Active | D94: Club Attendant | E94: 707-86-0595 | F94: 15348 Firmona Ave | G94: Lawndale, CA 90260 | H94: (213) 435-6047 | I94: 37961 | J94: 45785 | K94: =SUMIF(Data!$C$6:$V$29146,A94,Data!$V$6:$V$29146) -> 0 | L94: =IFERROR(K94*0.25,"") -> 0
A95: 100036535 | B95: Colton, Peggy A. | C95: Active | D95: Cashier, Concessions | E95: 436-82-5697 | F95: 1541 WEST JEFFERSON BLVD | G95: LOS ANGELES, CA 90018 | H95: (323) 615-8438 | I95: 17983 | J95: 43525 | K95: =SUMIF(Data!$C$6:$V$29146,A95,Data!$V$6:$V$29146) -> 0 | L95: =IFERROR(K95*0.25,"") -> 0
A96: 100054465 | B96: COPELAN, DESIREE | C96: Active | D96: Bartender, Premium | E96: 365-91-4030 | F96: 21625 Oak Orchard rd | G96: Newhall, CA 91321 | H96: (818) 731-1154 | I96: 30530 | J96: 44612 | K96: =SUMIF(Data!$C$6:$V$29146,A96,Data!$V$6:$V$29146) -> 0 | L96: =IFERROR(K96*0.25,"") -> 0
A97: 100093404 | B97: Coronado, Erik | C97: Active | D97: Club Attendant | E97: 624-49-9349 | F97: 1181 Browning Blvd. | G97: Los Angeles, CA 90037 | H97: (619) 384-1810 | I97: 38420 | J97: 45785 | K97: =SUMIF(Data!$C$6:$V$29146,A97,Data!$V$6:$V$29146) -> 0 | L97: =IFERROR(K97*0.25,"") -> 0
A98: 100084251 | B98: Cortes, Luis F. | C98: Active | D98: Cook 2 | E98: 623-15-8342 | F98: 2408 S Grand Ave Apt 2 | G98: Los Angeles, CA 90007-2649 | H98: (310) 266-5769 | I98: 36313 | J98: 45456 | K98: =SUMIF(Data!$C$6:$V$29146,A98,Data!$V$6:$V$29146) -> 0 | L98: =IFERROR(K98*0.25,"") -> 0
A99: 100087270 | B99: COSINA, SUSANA E. | C99: Active | D99: Runner, Suites | E99: 187-23-1246 | F99: 1332 W 99th Street | G99: Los Angeles, CA 90044 | H99: (323) 812-4418 | I99: 38559 | J99: 45546 | K99: =SUMIF(Data!$C$6:$V$29146,A99,Data!$V$6:$V$29146) -> 0 | L99: =IFERROR(K99*0.25,"") -> 0
A100: 100087279 | B100: Covarrubias, Jacqueline | C100: Active | D100: Club Attendant | E100: 623-37-6459 | F100: 6751 5th Ave | G100: Los Ángeles, CA 90043 | H100: (323) 212-8381 | I100: 37654 | J100: 45546 | K100: =SUMIF(Data!$C$6:$V$29146,A100,Data!$V$6:$V$29146) -> 0 | L100: =IFERROR(K100*0.25,"") -> 0
A101: 100049358 | B101: CRUZ, MARBELLA | C101: Active | D101: Cashier, Concessions | E101: 620-92-3918 | F101: 1639 E 33rd St | G101: Los Angeles, CA 90011 | H101: (323) 842-1305 | I101: 35174 | J101: 44392 | K101: =SUMIF(Data!$C$6:$V$29146,A101,Data!$V$6:$V$29146) -> 0 | L101: =IFERROR(K101*0.25,"") -> 0
A102: 100077507 | B102: Daffin, Jada C. | C102: Active | D102: Cashier, Concessions | E102: 623-49-8777 | F102: 8770 South Broadway | G102: Los Angeles, CA 90003 | H102: (661) 802-2786 | I102: 38391 | J102: 45322 | K102: =SUMIF(Data!$C$6:$V$29146,A102,Data!$V$6:$V$29146) -> 0 | L102: =IFERROR(K102*0.25,"") -> 0
...

Sheet Data
A1: PERSON TIME HISTORY REPORT by Working Dept
A2: 12/01/2025 Thru 01/05/2026
A3: Employee Type(s): FPVST
A5: Person Department | B5: Working Dept | C5: Person id | D5: Person Name | E5: PersonType | F5: EventID | G5: Event Name | H5: Event Start | I5: Facility | J5: Position | K5: PositionID | L5: Pos.Team | M5: Location | N5: Date | O5: Day of Week | P5: Weekend Event | Q5: IN Time | R5: OUT Time | S5: Rate | T5: RateType | U5: PayType | V5: Total Hrs | W5: Reg Hrs | X5: OT Hrs | Y5: DT Hrs | Z5: Other Hrs | AA5: Missed Meal Hrs | AB5: Missed Rest Hrs | AC5: Addl Event Pay | AD5: Commission | AE5: Tips | AF5: Tips CashedOut | AG5: Svc/Admin Chg | AH5: Reg Earnings | AI5: OT Earnings | AJ5: DT Earnings | AK5: Other Earnings | AL5: Missed Meal Earnings | AM5: Missed Rest Earnings | AN5: Allowances | AO5: Deductions | AP5: Total Earnings | AQ5: Is Late | AR5: Actual IN | AS5: Actual OUT | AT5: Sched IN | AU5: Sched OUT | AV5: Person Team/Area | AW5: HomeComponent | AX5: WkgComponent | AY5: Meal Hrs | AZ5: Meal Times | BA5: Approved Date | BB5: Flat Rate Reduction | BC5: Dress Allowance Hrs | BD5: WorkType_ID | BE5: WorkType Desc. | BF5: Comments | BG5: Event Additional Pay Hours 1 | BH5: Event Additional Pay Hours 2 | BI5: Special Handling Type | BJ5: Hours for Additional Pay Rules
A6: FCADM | B6: FCADM | C6: 100019803 | D6: ROBERTS, PAMALA B | E6: PT | F6: FDAILY | G6: DAILY WORK - LAFC | H6: 0.33333333 | I6: BC | J6: STAFFING COORDINATOR | K6: FASTCO04 | L6: FCADM | M6: BSADM | N6: 45993 | O6: Tuesday | P6: No | Q6: 0.26974537 | R6: 0.6291088 | S6: 25.75 | T6: H | U6: FA0065 | V6: 8.12 | W6: 8 | X6: 0.12 | AH6: 206 | AI6: 4.64 | AP6: 210.64 | AR6: 0.26974537 | AS6: 0.6291088 | AT6: 0.26974537 | AV6: FCADM - LAFC - ADMIN | AY6: 0.5 | AZ6: O-11:12:26 / I-12:09:08 | BA6: 12/03/2025 - PALCALA | BD6: FASTCO | BE6: STAFFING COORDINATOR | BF6: FIRST MEAL MANUALLY RECORDED | BG6: 0 | BH6: 0 | BJ6: 0
A7: FCADM | B7: FCADM | C7: 100019803 | D7: ROBERTS, PAMALA B | E7: PT | F7: FDAILY | G7: DAILY WORK - LAFC | H7: 0.33333333 | I7: BC | J7: STAFFING COORDINATOR | K7: FASTCO04 | L7: FCADM | M7: BSADM | N7: 45994 | O7: Wednesday | P7: No | Q7: 0.25965278 | R7: 0.60532407 | S7: 25.75 | T7: H | U7: FA0065 | V7: 7.8 | W7: 7.8 | AH7: 200.85 | AP7: 200.85 | AR7: 0.25965278 | AS7: 0.60532407 | AT7: 0.25965278 | AV7: FCADM - LAFC - ADMIN | AY7: 0.5 | AZ7: O-11:55:14 / I-12:25:37 | BA7: 12/08/2025 - PALCALA | BD7: FASTCO | BE7: STAFFING COORDINATOR | BG7: 0 | BH7: 0 | BJ7: 0
A8: FCADM | B8: FCADM | C8: 100019803 | D8: ROBERTS, PAMALA B | E8: PT | F8: FDAILY | G8: DAILY WORK - LAFC | H8: 0.33333333 | I8: BC | J8: STAFFING COORDINATOR | K8: FASTCO04 | L8: FCADM | M8: BSADM | N8: 45995 | O8: Thursday | P8: No | Q8: 0.26013889 | R8: 0.59525463 | S8: 25.75 | T8: H | U8: FA0065 | V8: 7.31 | W8: 7.31 | AH8: 188.23 | AP8: 188.23 | AR8: 0.26013889 | AS8: 0.59525463 | AT8: 0.26013889 | AV8: FCADM - LAFC - ADMIN | AY8: 0.73 | AZ8: O-10:43:10 / I-11:27:13 | BA8: 12/08/2025 - PALCALA | BD8: FASTCO | BE8: STAFFING COORDINATOR | BG8: 0 | BH8: 0 | BJ8: 0
A9: FCADM | B9: FCADM | C9: 100019803 | D9: ROBERTS, PAMALA B | E9: PT | F9: FDAILY | G9: DAILY WORK - LAFC | H9: 0.33333333 | I9: BC | J9: STAFFING COORDINATOR | K9: FASTCO04 | L9: FCADM | M9: BSADM | N9: 46000 | O9: Tuesday | P9: No | Q9: 0.28402778 | R9: 0.63136574 | S9: 25.75 | T9: H | U9: FA0065 | V9: 7.84 | W9: 7.84 | AH9: 201.88 | AP9: 201.88 | AR9: 0.28402778 | AS9: 0.63136574 | AT9: 0.28402778 | AV9: FCADM - LAFC - ADMIN | AY9: 0.5 | AZ9: O-12:33:55 / I-13:07:36 | BA9: 12/10/2025 - PALCALA | BD9: FASTCO | BE9: STAFFING COORDINATOR | BG9: 0 | BH9: 0 | BJ9: 0
A10: FCADM | B10: FCADM | C10: 100019803 | D10: ROBERTS, PAMALA B | E10: PT | F10: FDAILY | G10: DAILY WORK - LAFC | H10: 0.33333333 | I10: BC | J10: STAFFING COORDINATOR | K10: FASTCO04 | L10: FCADM | M10: BSADM | N10: 46001 | O10: Wednesday | P10: No | Q10: 0.26954861 | R10: 0.65673611 | S10: 25.75 | T10: H | U10: FA0065 | V10: 8.66 | W10: 8 | X10: 0.66 | AH10: 206 | AI10: 25.49 | AP10: 231.49 | AR10: 0.26954861 | AS10: 0.65673611 | AT10: 0.26954861 | AV10: FCADM - LAFC - ADMIN | AY10: 0.63 | AZ10: O-11:40:03 / I-12:17:48 | BA10: 12/12/2025 - PALCALA | BD10: FASTCO | BE10: STAFFING COORDINATOR | BG10: 0 | BH10: 0 | BJ10: 0
A11: FCADM | B11: FCADM | C11: 100019803 | D11: ROBERTS, PAMALA B | E11: PT | F11: FDAILY | G11: DAILY WORK - LAFC | H11: 0.33333333 | I11: BC | J11: STAFFING COORDINATOR | K11: FASTCO04 | L11: FCADM | M11: BSADM | N11: 46002 | O11: Thursday | P11: No | Q11: 0.625 | R11: 0.99032407 | S11: 25.75 | T11: H | U11: FA0065 | V11: 8.27 | W11: 8 | X11: 0.27 | AH11: 206 | AI11: 10.43 | AP11: 216.43 | AR11: 0.63314815 | AS11: 0.99032407 | AT11: 0.63314815 | AV11: FCADM - LAFC - ADMIN | AY11: 0.5 | BA11: 12/12/2025 - PALCALA | BD11: FASTCO | BE11: STAFFING COORDINATOR | BF11: FIRST MEAL MANUALLY RECORDED IN PUNCH MANUALLY RECORDED | BG11: 0 | BH11: 0 | BJ11: 0
A12: FCADM | B12: FCADM | C12: 100019803 | D12: ROBERTS, PAMALA B | E12: PT | F12: FDAILY | G12: DAILY WORK - LAFC | H12: 0.33333333 | I12: BC | J12: STAFFING COORDINATOR | K12: FASTCO04 | L12: FCADM | M12: BSADM | N12: 46003 | O12: Friday | P12: No | Q12: 0.33333333 | R12: 0.375 | S12: 25.75 | T12: H | U12: FA0065 | V12: 1 | W12: 1 | AH12: 25.75 | AP12: 25.75 | AV12: FCADM - LAFC - ADMIN | BA12: 12/17/2025 - PALCALA | BD12: FASTCO | BE12: STAFFING COORDINATOR | BF12: PAY 1 HR CALL WITH HR AND YOLANDA | BG12: 0 | BH12: 0 | BJ12: 0
A13: FCADM | B13: FCADM | C13: 100019803 | D13: ROBERTS, PAMALA B | E13: PT | F13: FDAILY | G13: DAILY WORK - LAFC | H13: 0.33333333 | I13: BC | J13: STAFFING COORDINATOR | K13: FASTCO04 | L13: FCADM | M13: BSADM | N13: 46007 | O13: Tuesday | P13: No | Q13: 0.32627315 | R13: 0.66900463 | S13: 25.75 | T13: H | U13: FA0065 | V13: 7.73 | W13: 7.73 | AH13: 199.05 | AP13: 199.05 | AR13: 0.32627315 | AS13: 0.66900463 | AT13: 0.32627315 | AV13: FCADM - LAFC - ADMIN | AY13: 0.5 | AZ13: O-12:59:01 / I-13:52:27 | BA13: 12/17/2025 - PALCALA | BD13: FASTCO | BE13: STAFFING COORDINATOR | BF13: FIRST MEAL MANUALLY RECORDED | BG13: 0 | BH13: 0 | BJ13: 0
A14: FCADM | B14: FCADM | C14: 100019803 | D14: ROBERTS, PAMALA B | E14: PT | F14: FDAILY | G14: DAILY WORK - LAFC | H14: 0.33333333 | I14: BC | J14: STAFFING COORDINATOR | K14: FASTCO04 | L14: FCADM | M14: BSADM | N14: 46008 | O14: Wednesday | P14: No | Q14: 0.30666667 | R14: 0.67686343 | S14: 25.75 | T14: H | U14: FA0065 | V14: 8.38 | W14: 8 | X14: 0.38 | AH14: 206 | AI14: 14.68 | AP14: 220.68 | AR14: 0.30666667 | AS14: 0.67686343 | AT14: 0.30666667 | AV14: FCADM - LAFC - ADMIN | AY14: 0.5 | AZ14: O-13:26:36 / I-13:57:34 | BA14: 12/23/2025 - PALCALA | BD14: FASTCO | BE14: STAFFING COORDINATOR | BG14: 0 | BH14: 0 | BJ14: 0
A15: FCADM | B15: FCADM | C15: 100019803 | D15: ROBERTS, PAMALA B | E15: PT | F15: FDAILY | G15: DAILY WORK - LAFC | H15: 0.33333333 | I15: BC | J15: STAFFING COORDINATOR | K15: FASTCO04 | L15: FCADM | M15: BSADM | N15: 46009 | O15: Thursday | P15: No | Q15: 0.29944444 | R15: 0.65347222 | S15: 25.75 | T15: H | U15: FA0065 | V15: 8 | W15: 8 | AH15: 206 | AP15: 206 | AR15: 0.29944444 | AT15: 0.29944444 | AV15: FCADM - LAFC - ADMIN | AY15: 0.5 | AZ15: O-11:12:47 / I-12:14:58 | BA15: 12/23/2025 - PALCALA | BD15: FASTCO | BE15: STAFFING COORDINATOR | BF15: OUT PUNCH MANUALLY RECORDED | BG15: 0 | BH15: 0 | BJ15: 0
A16: FCBAR | B16: FCBAR | C16: 100029715 | D16: DIAZ, ANA I | E16: PT | F16: FDAILY | G16: DAILY WORK - LAFC | H16: 0.33333333 | I16: BC | J16: FIELD CLUB 100 BARTENDER | K16: FB100B08 | L16: FCBAR | M16: BSPB4 | N16: 46006 | O16: Monday | P16: No | Q16: 0.42539352 | R16: 0.65424769 | S16: 17.87 | T16: 1 | U16: FB0025 | V16: 5.49 | W16: 5.49 | AH16: 98.11 | AP16: 98.11 | AQ16: Yes | AR16: 0.42539352 | AS16: 0.65424769 | AT16: 0.41666667 | AU16: 0.625 | AV16: FCBAR - CLUBS | BA16: 12/16/2025 - PALCALA | BD16: FBBBTD | BE16: BARTENDER | BG16: 0 | BH16: 0 | BJ16: 0
A17: FCBAR | B17: FCBAR | C17: 100029715 | D17: DIAZ, ANA I | E17: PT | F17: FDAILY | G17: DAILY WORK - LAFC | H17: 0.33333333 | I17: BC | J17: FIELD CLUB 100 BARTENDER | K17: FB100B05 | L17: FCBAR | M17: BSPB4 | N17: 46008 | O17: Wednesday | P17: No | Q17: 0.42304398 | R17: 0.65652778 | S17: 17.87 | T17: 1 | U17: FB0025 | V17: 5.6 | W17: 5.6 | AH17: 100.07 | AP17: 100.07 | AR17: 0.42304398 | AS17: 0.65652778 | AT17: 0.41666667 | AU17: 0.58333333 | AV17: FCBAR - CLUBS | BA17: 12/18/2025 - PALCALA | BD17: FBBBTD | BE17: BARTENDER | BG17: 0 | BH17: 0 | BJ17: 0
A18: FCBAR | B18: FCBAR | C18: 100036211 | D18: CHAIREZ, RICARDO | E18: PT | F18: FDAILY | G18: DAILY WORK - LAFC | H18: 0.33333333 | I18: BC | J18: SUNSET TERRACE DECK BARTENDER | K18: FBSTDB01 | L18: FCBAR | M18: BSP7 | N18: 46000 | O18: Tuesday | P18: No | Q18: 0.38695602 | R18: 0.57457176 | S18: 18.25 | T18: 1 | U18: FB0035 | V18: 4 | W18: 4 | AH18: 73 | AP18: 73 | AQ18: Yes | AR18: 0.38695602 | AS18: 0.56971065 | AT18: 0.375 | AU18: 0.58333333 | AV18: FCBAR - CLUBS | AY18: 0.5 | AZ18: O-09:49:03 / I-10:20:22 | BA18: 12/10/2025 - PALCALA | BD18: FBBBTD | BE18: BARTENDER | BG18: 0 | BH18: 0 | BJ18: 0
A19: FCBAR | B19: FCBAR | C19: 100036211 | D19: CHAIREZ, RICARDO | E19: PT | F19: FDAILY | G19: DAILY WORK - LAFC | H19: 0.33333333 | I19: BC | J19: FIELD CLUB 100 BARTENDER | K19: FB100B07 | L19: FCBAR | M19: BSPB4 | N19: 46006 | O19: Monday | P19: No | Q19: 0.41969907 | R19: 0.6540162 | S19: 18.25 | T19: 1 | U19: FB0035 | V19: 5.62 | W19: 5.62 | AH19: 102.57 | AP19: 102.57 | AR19: 0.41969907 | AS19: 0.6540162 | AT19: 0.41666667 | AU19: 0.625 | AV19: FCBAR - CLUBS | BA19: 12/16/2025 - PALCALA | BD19: FBBBTD | BE19: BARTENDER | BG19: 0 | BH19: 0 | BJ19: 0
A20: FCBAR | B20: FCBAR | C20: 100036211 | D20: CHAIREZ, RICARDO | E20: PT | F20: FDAILY | G20: DAILY WORK - LAFC | H20: 0.33333333 | I20: BC | J20: FIELD CLUB 100 BARTENDER | K20: FB100B01 | L20: FCBAR | M20: BSPB4 | N20: 46007 | O20: Tuesday | P20: No | Q20: 0.42508102 | R20: 0.634375 | S20: 18.25 | T20: 1 | U20: FB0035 | V20: 5.02 | W20: 5.02 | AH20: 91.62 | AP20: 91.62 | AQ20: Yes | AR20: 0.42508102 | AS20: 0.634375 | AT20: 0.41666667 | AU20: 0.625 | AV20: FCBAR - CLUBS | BA20: 12/17/2025 - PALCALA | BD20: FBBBTD | BE20: BARTENDER | BG20: 0 | BH20: 0 | BJ20: 0
A21: FCBAR | B21: FCBAR | C21: 100036211 | D21: CHAIREZ, RICARDO | E21: PT | F21: FDAILY | G21: DAILY WORK - LAFC | H21: 0.33333333 | I21: BC | J21: FIELD CLUB 100 BARTENDER | K21: FB100B01 | L21: FCBAR | M21: BSPB4 | N21: 46008 | O21: Wednesday | P21: No | Q21: 0.44888889 | R21: 0.65820602 | S21: 18.25 | T21: 1 | U21: FB0035 | V21: 5.02 | W21: 5.02 | AH21: 91.62 | AP21: 91.62 | AR21: 0.44888889 | AS21: 0.65820602 | AT21: 0.44444444 | AU21: 0.58333333 | AV21: FCBAR - CLUBS | BA21: 12/18/2025 - PALCALA | BD21: FBBBTD | BE21: BARTENDER | BG21: 0 | BH21: 0 | BJ21: 0
A22: FCBAR | B22: FCBAR | C22: 100049378 | D22: MUNGUIA, JOSE | E22: PT | F22: FDAILY | G22: DAILY WORK - LAFC | H22: 0.33333333 | I22: BC | J22: FIELD CLUB 100 BARTENDER | K22: FB100B02 | L22: FCBAR | M22: BSPB4 | N22: 46008 | O22: Wednesday | P22: No | Q22: 0.42711806 | R22: 0.66439815 | S22: 17.87 | T22: 1 | U22: FB0025 | V22: 5.69 | W22: 5.69 | AH22: 101.68 | AP22: 101.68 | AQ22: Yes | AR22: 0.42711806 | AS22: 0.66439815 | AT22: 0.41666667 | AU22: 0.58333333 | AV22: FCBAR - CLUBS | BA22: 12/18/2025 - PALCALA | BD22: FBBBTD | BE22: BARTENDER | BG22: 0 | BH22: 0 | BJ22: 0
A23: FCBAR | B23: FCBAR | C23: 100064556 | D23: ARROYO, ISIAH | E23: PT | F23: FDAILY | G23: DAILY WORK - LAFC | H23: 0.33333333 | I23: BC | J23: DAILY WORK SUPERVISOR | K23: FADSUP03 | L23: FCBAR | M23: FCBARS | N23: 46007 | O23: Tuesday | P23: No | Q23: 0.43375 | R23: 0.63072917 | S23: 20 | T23: H | U23: FB0042 | V23: 4.73 | W23: 4.73 | AH23: 94.6 | AP23: 94.6 | AQ23: Yes | AR23: 0.43375 | AS23: 0.63072917 | AT23: 0.41666667 | AU23: 0.625 | AV23: FCBAR - CLUBS | BA23: 12/17/2025 - PALCALA | BD23: FBSUP | BE23: PREMIUM SUPERVISOR | BG23: 0 | BH23: 0 | BJ23: 0
A24: FCBAR | B24: FCBAR | C24: 100084246 | D24: GREEN, NATHANIEL | E24: PT | F24: FDAILY | G24: DAILY WORK - LAFC | H24: 0.33333333 | I24: BC | J24: DAILY WORK SUPERVISOR | K24: FADSUP01 | L24: FCBAR | M24: FCBARS | N24: 46006 | O24: Monday | P24: No | Q24: 0.46107639 | R24: 0.58068287 | S24: 20 | T24: H | U24: FB0042 | V24: 2.87 | W24: 2.87 | AH24: 57.4 | AP24: 57.4 | AR24: 0.46107639 | AS24: 0.58068287 | AT24: 0.45833333 | AU24: 0.625 | AV24: FCBAR - CLUBS | BA24: 12/16/2025 - PALCALA | BD24: FBSUP | BE24: PREMIUM SUPERVISOR | BG24: 0 | BH24: 0 | BJ24: 0
A25: FCBAR | B25: FCBAR | C25: 100084246 | D25: GREEN, NATHANIEL | E25: PT | F25: FDAILY | G25: DAILY WORK - LAFC | H25: 0.33333333 | I25: BC | J25: DAILY WORK SUPERVISOR | K25: FADSUP02 | L25: FCBAR | M25: FCBARS | N25: 46007 | O25: Tuesday | P25: No | Q25: 0.43056713 | R25: 0.63087963 | S25: 20 | T25: H | U25: FB0042 | V25: 4.81 | W25: 4.81 | AH25: 96.2 | AP25: 96.2 | AQ25: Yes | AR25: 0.43056713 | AS25: 0.63087963 | AT25: 0.41666667 | AU25: 0.625 | AV25: FCBAR - CLUBS | BA25: 12/17/2025 - PALCALA | BD25: FBSUP | BE25: PREMIUM SUPERVISOR | BG25: 0 | BH25: 0 | BJ25: 0
A26: FCBAR | B26: FCBAR | C26: 100087211 | D26: LEAL SILVA, MARCO A | E26: PT | F26: FDAILY | G26: DAILY WORK - LAFC | H26: 0.33333333 | I26: BC | J26: SUNSET TERRACE DECK BARBACK | K26: FBSTDK01 | L26: FCBAR | M26: BSP7 | N26: 46000 | O26: Tuesday | P26: No | Q26: 0.37774306 | R26: 0.56984954 | S26: 17.87 | T26: 1 | U26: FB0010 | V26: 4.61 | W26: 4.61 | AH26: 82.38 | AP26: 82.38 | AR26: 0.37774306 | AS26: 0.56984954 | AT26: 0.375 | AU26: 0.58333333 | AV26: FCBAR - CLUBS | BA26: 12/10/2025 - PALCALA | BD26: FBBBBK | BE26: BARBACK | BG26: 0 | BH26: 0 | BJ26: 0
A27: FCBAR | B27: FCBAR | C27: 100087211 | D27: LEAL SILVA, MARCO A | E27: PT | F27: FDAILY | G27: DAILY WORK - LAFC | H27: 0.33333333 | I27: BC | J27: FIELD CLUB 100 BARBACK | K27: FB100801 | L27: FCBAR | M27: BSPB4 | N27: 46006 | O27: Monday | P27: No | Q27: 0.41172454 | R27: 0.58533565 | S27: 17.87 | T27: 1 | U27: FB0010 | V27: 4.17 | W27: 4.17 | AH27: 74.52 | AP27: 74.52 | AR27: 0.41172454 | AS27: 0.58533565 | AT27: 0.41666667 | AU27: 0.625 | AV27: FCBAR - CLUBS | BA27: 12/16/2025 - PALCALA | BD27: FBBBBK | BE27: BARBACK | BG27: 0 | BH27: 0 | BJ27: 0
A28: FCBAR | B28: FCBAR | C28: 100087211 | D28: LEAL SILVA, MARCO A | E28: PT | F28: FDAILY | G28: DAILY WORK - LAFC | H28: 0.33333333 | I28: BC | J28: FIELD CLUB 100 BARBACK | K28: FB100801 | L28: FCBAR | M28: BSPB4 | N28: 46007 | O28: Tuesday | P28: No | Q28: 0.41186343 | R28: 0.63423611 | S28: 17.87 | T28: 1 | U28: FB0010 | V28: 5.34 | W28: 5.34 | AH28: 95.43 | AP28: 95.43 | AR28: 0.41186343 | AS28: 0.63423611 | AT28: 0.41666667 | AU28: 0.625 | AV28: FCBAR - CLUBS | BA28: 12/17/2025 - PALCALA | BD28: FBBBBK | BE28: BARBACK | BG28: 0 | BH28: 0 | BJ28: 0
A29: FCBAR | B29: FCBAR | C29: 100087211 | D29: LEAL SILVA, MARCO A | E29: PT | F29: FDAILY | G29: DAILY WORK - LAFC | H29: 0.33333333 | I29: BC | J29: FIELD CLUB 100 BARBACK | K29: FB100801 | L29: FCBAR | M29: BSPB4 | N29: 46008 | O29: Wednesday | P29: No | Q29: 0.4183912 | R29: 0.62896991 | S29: 17.87 | T29: 1 | U29: FB0010 | V29: 5.05 | W29: 5.05 | AH29: 90.24 | AP29: 90.24 | AR29: 0.4183912 | AS29: 0.62896991 | AT29: 0.41666667 | AU29: 0.58333333 | AV29: FCBAR - CLUBS | BA29: 12/18/2025 - PALCALA | BD29: FBBBBK | BE29: BARBACK | BG29: 0 | BH29: 0 | BJ29: 0
A30: FCCAT | B30: FCCAT | C30: 100002210 | D30: QUINTANAR, ROSEMARY | E30: PT | F30: F25C96 | G30: ABM HOLIDAY DINNER - CATERING | H30: 0.70833333 | I30: BS | J30: CATERING SERVER | K30: FCCAT74 | L30: FCCAT | M30: BSCAT | N30: 45994 | O30: Wednesday | P30: No | Q30: 0.57721065 | R30: 0.88244213 | S30: 22 | T30: 1 | U30: FC0030 | V30: 6.83 | W30: 6.83 | AH30: 150.26 | AP30: 150.26 | AR30: 0.57721065 | AS30: 0.88244213 | AT30: 0.58333333 | AU30: 0.85416667 | AV30: FCCAT - LAFC - CATERING | AY30: 0.5 | AZ30: O-15:03:51 / I-15:34:10 | BA30: 12/08/2025 - PALCALA | BD30: FCBSRV | BE30: CATERING SERVER | BG30: 0 | BH30: 0 | BJ30: 0
A31: FCCAT | B31: FCCAT | C31: 100002210 | D31: QUINTANAR, ROSEMARY | E31: PT | F31: F25C98 | G31: LA CLEANTECH INCUBATOR DAY 1 - CATERING | H31: 0.66666667 | I31: BS | J31: CATERING SERVER | K31: FCCAT24 | L31: FCCAT | M31: BSCAT | N31: 45999 | O31: Monday | P31: No | Q31: 0.49357639 | R31: 0.7741088 | S31: 22 | T31: 1 | U31: FC0030 | V31: 6.23 | W31: 6.23 | AH31: 137.06 | AP31: 137.06 | AR31: 0.49357639 | AS31: 0.7741088 | AT31: 0.5 | AU31: 0.85416667 | AV31: FCCAT - LAFC - CATERING | AY31: 0.5 | AZ31: O-14:10:36 / I-14:41:19 | BA31: 12/10/2025 - PALCALA | BD31: FCBSRV | BE31: CATERING SERVER | BG31: 0 | BH31: 0 | BJ31: 0
A32: FCCAT | B32: FCCAT | C32: 100002210 | D32: QUINTANAR, ROSEMARY | E32: PT | F32: F25C99 | G32: LA CLEANTECH INCUBATOR - DAY 2 - CATERING | H32: 0.375 | I32: BS | J32: CATERING SERVER | K32: FCCAT23 | L32: FCCAT | M32: BSCAT | N32: 46000 | O32: Tuesday | P32: No | Q32: 0.28822917 | R32: 0.69912037 | S32: 22 | T32: 1 | U32: FC0030 | V32: 9.86 | W32: 8 | X32: 1.86 | AH32: 176 | AI32: 61.38 | AP32: 237.38 | AR32: 0.28822917 | AS32: 0.69912037 | AT32: 0.29166667 | AU32: 0.625 | AV32: FCCAT - LAFC - CATERING | BA32: 12/10/2025 - PALCALA | BD32: FCBSRV | BE32: CATERING SERVER | BG32: 0 | BH32: 0 | BJ32: 0
A33: FCCAT | B33: FCCAT | C33: 100002210 | D33: QUINTANAR, ROSEMARY | E33: PT | F33: F25C00 | G33: BEECAN HOLIDAY PARTY - CATERING | H33: 0.79166667 | I33: BS | J33: CATERING SERVER | K33: FCCAT29 | L33: FCCAT | M33: BSCAT | N33: 46002 | O33: Thursday | P33: No | Q33: 0.71040509 | R33: 0.00040509259 | S33: 22 | T33: 1 | U33: FC0030 | V33: 7.96 | W33: 6.96 | AA33: 1 | AH33: 153.12 | AL33: 22 | AP33: 175.12 | AR33: 0.71040509 | AS33: 0.00040509259 | AT33: 0.70833333 | AU33: 1 | AV33: FCCAT - LAFC - CATERING | BA33: 12/16/2025 - PALCALA | BD33: FCBSRV | BE33: CATERING SERVER | BF33: MEAL PREMIUM | BG33: 0 | BH33: 0 | BJ33: 0
A34: FCCAT | B34: FCCAT | C34: 100002210 | D34: QUINTANAR, ROSEMARY | E34: PT | F34: F25C24 | G34: FISHER PHILLIPS HOLIDAY PARTY - CATERING | H34: 0.79166667 | I34: BS | J34: CATERING SERVER | K34: FCCAT22 | L34: FCCAT | M34: BSCAT | N34: 46003 | O34: Friday | P34: No | Q34: 0.68447917 | R34: 0.98534722 | S34: 22 | T34: 1 | U34: FC0030 | V34: 6.72 | W34: 6.72 | AH34: 147.84 | AP34: 147.84 | AR34: 0.68447917 | AS34: 0.98534722 | AT34: 0.6875 | AU34: 0.97916667 | AV34: FCCAT - LAFC - CATERING | AY34: 0.5 | AZ34: O-16:36:22 / I-17:06:40 | BA34: 12/16/2025 - PALCALA | BD34: FCBSRV | BE34: CATERING SERVER | BG34: 0 | BH34: 0 | BJ34: 0
A35: FCBAR | B35: FCCAT | C35: 100029715 | D35: DIAZ, ANA I | E35: PT | F35: F25C00 | G35: BEECAN HOLIDAY PARTY - CATERING | H35: 0.79166667 | I35: BS | J35: CATERING BARTENDER | K35: FCCATB11 | L35: FCCAT | M35: BSCAT | N35: 46002 | O35: Thursday | P35: No | Q35: 0.68310185 | R35: 0.99416667 | S35: 22 | T35: 1 | U35: FC020 | V35: 6.97 | W35: 6.97 | AE35: 175 | AH35: 153.34 | AP35: 328.34 | AR35: 0.68310185 | AS35: 0.99416667 | AT35: 0.6875 | AU35: 0.020833333 | AV35: FCBAR - | AY35: 0.5 | AZ35: O-16:23:56 / I-16:54:28 | BA35: 12/15/2025 - PALCALA | BD35: FCBART | BE35: CATERING BARTENDER | BG35: 0 | BH35: 0 | BJ35: 0
A36: FCBAR | B36: FCCAT | C36: 100029801 | D36: ALVARADO, LETICIA | E36: PT | F36: F25C00 | G36: BEECAN HOLIDAY PARTY - CATERING | H36: 0.79166667 | I36: BS | J36: CATERING BARTENDER | K36: FCCATB18 | L36: FCCAT | M36: BSCAT | N36: 46002 | O36: Thursday | P36: No | Q36: 0.68284722 | R36: 0.98175926 | S36: 22 | T36: 1 | U36: FC020 | V36: 6.67 | W36: 6.67 | AE36: 175 | AH36: 146.74 | AP36: 321.74 | AR36: 0.68284722 | AS36: 0.98175926 | AT36: 0.6875 | AU36: 1 | AV36: FCBAR - | AY36: 0.5 | BA36: 12/15/2025 - PALCALA | BD36: FCBART | BE36: CATERING BARTENDER | BF36: FIRST MEAL MANUALLY RECORDED | BG36: 0 | BH36: 0 | BJ36: 0
A37: FCCAT | B37: FCCAT | C37: 100030153 | D37: SOSA, VALERIA R | E37: PT | F37: FDAILY | G37: DAILY WORK - LAFC | H37: 0.33333333 | I37: BC | J37: CATERING SERVER | K37: FCCAT21 | L37: FCCAT | M37: BSCAT | N37: 45992 | O37: Monday | P37: No | Q37: 0.41350694 | R37: 0.65731481 | S37: 22 | T37: 1 | U37: FC0030 | V37: 5.85 | W37: 5.85 | AH37: 128.7 | AP37: 128.7 | AR37: 0.41350694 | AS37: 0.65731481 | AT37: 0.41666667 | AU37: 0.66666667 | AV37: FCCAT - LAFC - CATERING | BA37: 12/02/2025 - PALCALA | BD37: FCBSRV | BE37: CATERING SERVER | BG37: 0 | BH37: 0 | BJ37: 0
A38: FCCAT | B38: FCCAT | C38: 100030153 | D38: SOSA, VALERIA R | E38: PT | F38: F25C95 | G38: GLORIA TREVI PRESS EVENT - CATERING | H38: 0.66666667 | I38: BS | J38: CATERING SERVER | K38: FCCAT22 | L38: FCCAT | M38: BSCAT | N38: 45993 | O38: Tuesday | P38: No | Q38: 0.28736111 | R38: 0.60819444 | S38: 22 | T38: 1 | U38: FC0030 | V38: 7.11 | W38: 7.11 | AH38: 156.42 | AP38: 156.42 | AR38: 0.28736111 | AS38: 0.60819444 | AT38: 0.29166667 | AU38: 0.625 | AV38: FCCAT - LAFC - CATERING | AY38: 0.59 | AZ38: O-08:43:29 / I-09:18:48 | BA38: 12/03/2025 - PALCALA | BD38: FCBSRV | BE38: CATERING SERVER | BG38: 0 | BH38: 0 | BJ38: 0
A39: FCCAT | B39: FCCAT | C39: 100030153 | D39: SOSA, VALERIA R | E39: PT | F39: F25C96 | G39: ABM HOLIDAY DINNER - CATERING | H39: 0.70833333 | I39: BS | J39: CATERING SERVER | K39: FCCAT68 | L39: FCCAT | M39: BSCAT | N39: 45994 | O39: Wednesday | P39: No | Q39: 0.57638889 | R39: 0.88194444 | S39: 22 | T39: 1 | U39: FC0030 | V39: 6.83 | W39: 6.83 | AH39: 150.26 | AP39: 150.26 | AT39: 0.58333333 | AU39: 0.875 | AV39: FCCAT - LAFC - CATERING | AY39: 0.5 | BA39: 12/10/2025 - PALCALA | BD39: FCBSRV | BE39: CATERING SERVER | BF39: IN AND OUT PUNCH/FIRST MEAL MANUALLY RECORDED | BG39: 0 | BH39: 0 | BJ39: 0
A40: FCCAT | B40: FCCAT | C40: 100030153 | D40: SOSA, VALERIA R | E40: PT | F40: F25C97 | G40: FINNISH MOBILITY SHOWCASE - CATERING | H40: 0.70833333 | I40: BS | J40: CATERING SERVER | K40: FCCAT23 | L40: FCCAT | M40: BSCAT | N40: 45995 | O40: Thursday | P40: No | Q40: 0.58825231 | R40: 0.8437963 | S40: 22 | T40: 1 | U40: FC0030 | V40: 5.63 | W40: 5.63 | AH40: 123.86 | AP40: 123.86 | AR40: 0.58825231 | AS40: 0.8437963 | AT40: 0.58333333 | AU40: 0.85416667 | AV40: FCCAT - LAFC - CATERING | AY40: 0.5 | AZ40: O-15:11:43 / I-15:42:39 | BA40: 12/08/2025 - PALCALA | BD40: FCBSRV | BE40: CATERING SERVER | BG40: 0 | BH40: 0 | BJ40: 0
A41: FCCAT | B41: FCCAT | C41: 100030153 | D41: SOSA, VALERIA R | E41: PT | F41: FDAILY | G41: DAILY WORK - LAFC | H41: 0.33333333 | I41: BC | J41: CATERING SERVER | K41: FCCAT21 | L41: FCCAT | M41: BSCAT | N41: 45998 | O41: Sunday | P41: Yes | Q41: 0.3721875 | R41: 0.61778935 | S41: 22 | T41: 1 | U41: FC0030 | V41: 5.89 | W41: 5.89 | AH41: 129.58 | AP41: 129.58 | AR41: 0.3721875 | AS41: 0.61778935 | AT41: 0.375 | AU41: 0.625 | AV41: FCCAT - LAFC - CATERING | BA41: 12/08/2025 - PALCALA | BD41: FCBSRV | BE41: CATERING SERVER | BG41: 0 | BH41: 0 | BJ41: 0
A42: FCCAT | B42: FCCAT | C42: 100030153 | D42: SOSA, VALERIA R | E42: PT | F42: F25C98 | G42: LA CLEANTECH INCUBATOR DAY 1 - CATERING | H42: 0.66666667 | I42: BS | J42: CATERING SERVER | K42: FCCAT23 | L42: FCCAT | M42: BSCAT | N42: 45999 | O42: Monday | P42: No | Q42: 0.30756944 | R42: 0.78715278 | S42: 22 | T42: 1 | U42: FC0030 | V42: 11.01 | W42: 8 | X42: 3.01 | AH42: 176 | AI42: 99.33 | AP42: 275.33 | AR42: 0.30756944 | AS42: 0.78715278 | AT42: 0.3125 | AU42: 0.625 | AV42: FCCAT - LAFC - CATERING | AY42: 0.5 | AZ42: O-11:47:15 / I-12:19:18 | BA42: 12/10/2025 - PALCALA | BD42: FCBSRV | BE42: CATERING SERVER | BG42: 0 | BH42: 0 | BJ42: 0
A43: FCCAT | B43: FCCAT | C43: 100030153 | D43: SOSA, VALERIA R | E43: PT | F43: F25C99 | G43: LA CLEANTECH INCUBATOR - DAY 2 - CATERING | H43: 0.375 | I43: BS | J43: CATERING SERVER | K43: FCCAT25 | L43: FCCAT | M43: BSCAT | N43: 46000 | O43: Tuesday | P43: No | Q43: 0.3125 | R43: 0.75 | S43: 22 | T43: 1 | U43: FC0030 | V43: 10 | W43: 8 | X43: 2 | AH43: 176 | AI43: 66 | AP43: 242 | AT43: 0.29166667 | AU43: 0.625 | AV43: FCCAT - LAFC - CATERING | AY43: 0.5 | BA43: 12/10/2025 - PALCALA | BD43: FCBSRV | BE43: CATERING SERVER | BF43: IN AND OUT PUNCH/FIRST MEAL MANUALLY RECORDED | BG43: 0 | BH43: 0 | BJ43: 0
A44: FCCAT | B44: FCCAT | C44: 100030153 | D44: SOSA, VALERIA R | E44: PT | F44: FDAILY | G44: DAILY WORK - LAFC | H44: 0.33333333 | I44: BC | J44: CATERING SERVER | K44: FCCAT22 | L44: FCCAT | M44: BSCAT | N44: 46001 | O44: Wednesday | P44: No | Q44: 0.50694444 | R44: 0.75 | S44: 22 | T44: 1 | U44: FC0030 | V44: 5.83 | W44: 5.83 | AH44: 128.26 | AP44: 128.26 | AT44: 0.45833333 | AU44: 0.75 | AV44: FCCAT - LAFC - CATERING | BA44: 12/15/2025 - PALCALA | BD44: FCBSRV | BE44: CATERING SERVER | BF44: IN AND OUT PUNCH/FIRST MEAL MANUALLY RECORDED | BG44: 0 | BH44: 0 | BJ44: 0
A45: FCCAT | B45: FCCAT | C45: 100030153 | D45: SOSA, VALERIA R | E45: PT | F45: F25C00 | G45: BEECAN HOLIDAY PARTY - CATERING | H45: 0.79166667 | I45: BS | J45: CATERING SERVER | K45: FCCAT76 | L45: FCCAT | M45: BSCAT | N45: 46002 | O45: Thursday | P45: No | Q45: 0.69013889 | R45: 0.99349537 | S45: 22 | T45: 1 | U45: FC0030 | V45: 6.78 | W45: 6.78 | AH45: 149.16 | AP45: 149.16 | AR45: 0.69013889 | AS45: 0.99349537 | AT45: 0.6875 | AU45: 1 | AV45: FCCAT - LAFC - CATERING | AY45: 0.5 | AZ45: O-16:43:53 / I-17:18:03 | BA45: 12/16/2025 - PALCALA | BD45: FCBSRV | BE45: CATERING SERVER | BG45: 0 | BH45: 0 | BJ45: 0
A46: FCCAT | B46: FCCAT | C46: 100030153 | D46: SOSA, VALERIA R | E46: PT | F46: F25C24 | G46: FISHER PHILLIPS HOLIDAY PARTY - CATERING | H46: 0.79166667 | I46: BS | J46: CATERING SERVER | K46: FCCAT24 | L46: FCCAT | M46: BSCAT | N46: 46003 | O46: Friday | P46: No | Q46: 0.69366898 | R46: 0.98527778 | S46: 22 | T46: 1 | U46: FC0030 | V46: 6.5 | W46: 6.5 | AH46: 143 | AP46: 143 | AR46: 0.69366898 | AS46: 0.98527778 | AT46: 0.6875 | AU46: 0.97916667 | AV46: FCCAT - LAFC - CATERING | AY46: 0.5 | AZ46: O-16:47:31 / I-17:19:19 | BA46: 12/16/2025 - PALCALA | BD46: FCBSRV | BE46: CATERING SERVER | BG46: 0 | BH46: 0 | BJ46: 0
A47: FCCAT | B47: FCCAT | C47: 100030153 | D47: SOSA, VALERIA R | E47: PT | F47: F25S39 | G47: 3252 END OF YEAR CELEBRATION - CATERING | H47: 0.6875 | I47: BS | J47: CATERING SERVER | K47: FCCAT21 | L47: FCCAT | M47: BSCAT | N47: 46005 | O47: Sunday | P47: Yes | Q47: 0.58175926 | R47: 0.89320602 | S47: 22 | T47: 1 | U47: FC0030 | V47: 6.97 | W47: 6.97 | AH47: 153.34 | AP47: 153.34 | AR47: 0.58175926 | AS47: 0.89320602 | AT47: 0.58333333 | AU47: 0.89583333 | AV47: FCCAT - LAFC - CATERING | AY47: 0.5 | AZ47: O-15:14:00 / I-15:45:00 | BA47: 12/16/2025 - PALCALA | BD47: FCBSRV | BE47: CATERING SERVER | BG47: 0 | BH47: 0 | BJ47: 0
A48: FCCAT | B48: FCCAT | C48: 100030153 | D48: SOSA, VALERIA R | E48: PT | F48: F25S40 | G48: HEAD COACH PRESS CONFERENCE - CATERING | H48: 0.47916667 | I48: BS | J48: CATERING SERVER | K48: FCCAT22 | L48: FCCAT | M48: BSCAT | N48: 46006 | O48: Monday | P48: No | Q48: 0.28936343 | R48: 0.61949074 | S48: 22 | T48: 1 | U48: FC0030 | V48: 7.42 | W48: 7.42 | AH48: 163.24 | AP48: 163.24 | AR48: 0.28936343 | AS48: 0.61949074 | AT48: 0.29166667 | AU48: 0.625 | AV48: FCCAT - LAFC - CATERING | AY48: 0.5 | AZ48: O-10:17:26 / I-10:48:11 | BA48: 12/16/2025 - PALCALA | BD48: FCBSRV | BE48: CATERING SERVER | BG48: 0 | BH48: 0 | BJ48: 0
A49: FCCAT | B49: FCCAT | C49: 100030854 | D49: GUENDULAIN ALCALA, EDUARDO A | E49: PT | F49: F25C96 | G49: ABM HOLIDAY DINNER - CATERING | H49: 0.70833333 | I49: BS | J49: CATERING SERVER | K49: FCCAT70 | L49: FCCAT | M49: BSCAT | N49: 45994 | O49: Wednesday | P49: No | Q49: 0.57674769 | R49: 0.85481481 | S49: 22 | T49: 1 | U49: FC0030 | V49: 6.17 | W49: 6.17 | AH49: 135.74 | AP49: 135.74 | AR49: 0.57674769 | AS49: 0.85481481 | AT49: 0.58333333 | AU49: 0.875 | AV49: FCCAT - LAFC - CATERING | AY49: 0.5 | AZ49: O-15:06:15 / I-15:37:05 | BA49: 12/08/2025 - PALCALA | BD49: FCBSRV | BE49: CATERING SERVER | BG49: 0 | BH49: 0 | BJ49: 0
A50: FCCAT | B50: FCCAT | C50: 100030897 | D50: HERNANDEZ, JESUS E | E50: PT | F50: F25C95 | G50: GLORIA TREVI PRESS EVENT - CATERING | H50: 0.66666667 | I50: BS | J50: CATERING SERVER | K50: FCCAT21 | L50: FCCAT | M50: BSCAT | N50: 45993 | O50: Tuesday | P50: No | Q50: 0.32920139 | R50: 0.60293981 | S50: 22 | T50: 1 | U50: FC0030 | V50: 6.07 | W50: 6.07 | AH50: 133.54 | AP50: 133.54 | AR50: 0.32920139 | AS50: 0.60293981 | AT50: 0.33333333 | AU50: 0.625 | AV50: FCCAT - LAFC - CATERING | AY50: 0.5 | AZ50: O-09:00:50 / I-09:31:15 | BA50: 12/03/2025 - PALCALA | BD50: FCBSRV | BE50: CATERING SERVER | BG50: 0 | BH50: 0 | BJ50: 0
A51: FCCAT | B51: FCCAT | C51: 100030897 | D51: HERNANDEZ, JESUS E | E51: PT | F51: F25C96 | G51: ABM HOLIDAY DINNER - CATERING | H51: 0.70833333 | I51: BS | J51: CATERING SERVER | K51: FCCAT69 | L51: FCCAT | M51: BSCAT | N51: 45994 | O51: Wednesday | P51: No | Q51: 0.57664352 | R51: 0.8546875 | S51: 22 | T51: 1 | U51: FC0030 | V51: 6.17 | W51: 6.17 | AH51: 135.74 | AP51: 135.74 | AR51: 0.57664352 | AS51: 0.8546875 | AT51: 0.58333333 | AU51: 0.875 | AV51: FCCAT - LAFC - CATERING | AY51: 0.5 | AZ51: O-15:06:02 / I-15:36:28 | BA51: 12/08/2025 - PALCALA | BD51: FCBSRV | BE51: CATERING SERVER | BG51: 0 | BH51: 0 | BJ51: 0
A52: FCCAT | B52: FCCAT | C52: 100030897 | D52: HERNANDEZ, JESUS E | E52: PT | F52: F25C97 | G52: FINNISH MOBILITY SHOWCASE - CATERING | H52: 0.70833333 | I52: BS | J52: CATERING SERVER | K52: FCCAT22 | L52: FCCAT | M52: BSCAT | N52: 45995 | O52: Thursday | P52: No | Q52: 0.5766088 | R52: 0.85021991 | S52: 22 | T52: 1 | U52: FC0030 | V52: 6.07 | W52: 6.07 | AH52: 133.54 | AP52: 133.54 | AR52: 0.5766088 | AS52: 0.85021991 | AT52: 0.58333333 | AU52: 0.85416667 | AV52: FCCAT - LAFC - CATERING | AY52: 0.5 | AZ52: O-15:15:17 / I-15:45:30 | BA52: 12/08/2025 - PALCALA | BD52: FCBSRV | BE52: CATERING SERVER | BG52: 0 | BH52: 0 | BJ52: 0
A53: FCCAT | B53: FCCAT | C53: 100030897 | D53: HERNANDEZ, JESUS E | E53: PT | F53: F25C98 | G53: LA CLEANTECH INCUBATOR DAY 1 - CATERING | H53: 0.66666667 | I53: BS | J53: CATERING SERVER | K53: FCCAT22 | L53: FCCAT | M53: BSCAT | N53: 45999 | O53: Monday | P53: No | Q53: 0.30570602 | R53: 0.6605787 | S53: 22 | T53: 1 | U53: FC0030 | V53: 8.02 | W53: 8 | X53: 0.02 | AH53: 176 | AI53: 0.66 | AP53: 176.66 | AR53: 0.30570602 | AS53: 0.6605787 | AT53: 0.3125 | AU53: 0.58333333 | AV53: FCCAT - LAFC - CATERING | AY53: 0.5 | AZ53: O-09:46:08 / I-10:16:14 | BA53: 12/10/2025 - PALCALA | BD53: FCBSRV | BE53: CATERING SERVER | BG53: 0 | BH53: 0 | BJ53: 0
A54: FCCAT | B54: FCCAT | C54: 100030897 | D54: HERNANDEZ, JESUS E | E54: PT | F54: F25C99 | G54: LA CLEANTECH INCUBATOR - DAY 2 - CATERING | H54: 0.375 | I54: BS | J54: CATERING SERVER | K54: FCCAT24 | L54: FCCAT | M54: BSCAT | N54: 46000 | O54: Tuesday | P54: No | Q54: 0.28484954 | R54: 0.74454861 | S54: 22 | T54: 1 | U54: FC0030 | V54: 10.53 | W54: 8 | X54: 2.53 | AH54: 176 | AI54: 83.49 | AP54: 259.49 | AR54: 0.28484954 | AS54: 0.74454861 | AT54: 0.29166667 | AU54: 0.625 | AV54: FCCAT - LAFC - CATERING | AY54: 0.5 | AZ54: O-10:57:10 / I-11:27:11 | BA54: 12/10/2025 - PALCALA | BD54: FCBSRV | BE54: CATERING SERVER | BG54: 0 | BH54: 0 | BJ54: 0
A55: FCCAT | B55: FCCAT | C55: 100030897 | D55: HERNANDEZ, JESUS E | E55: PT | F55: F25C00 | G55: BEECAN HOLIDAY PARTY - CATERING | H55: 0.79166667 | I55: BS | J55: CATERING SERVER | K55: FCCAT75 | L55: FCCAT | M55: BSCAT | N55: 46002 | O55: Thursday | P55: No | Q55: 0.70168981 | R55: 0.00011574074 | S55: 22 | T55: 1 | U55: FC0030 | V55: 6.66 | W55: 6.66 | AH55: 146.52 | AP55: 146.52 | AR55: 0.70168981 | AS55: 0.00011574074 | AT55: 0.70833333 | AU55: 1 | AV55: FCCAT - LAFC - CATERING | AY55: 0.5 | AZ55: O-16:57:56 / I-17:28:21 | BA55: 12/16/2025 - PALCALA | BD55: FCBSRV | BE55: CATERING SERVER | BG55: 0 | BH55: 0 | BJ55: 0
A56: FCCAT | B56: FCCAT | C56: 100030897 | D56: HERNANDEZ, JESUS E | E56: PT | F56: F25C24 | G56: FISHER PHILLIPS HOLIDAY PARTY - CATERING | H56: 0.79166667 | I56: BS | J56: CATERING SERVER | K56: FCCAT23 | L56: FCCAT | M56: BSCAT | N56: 46003 | O56: Friday | P56: No | Q56: 0.68091435 | R56: 0.90677083 | S56: 22 | T56: 1 | U56: FC0030 | V56: 4.92 | W56: 4.92 | AH56: 108.24 | AP56: 108.24 | AR56: 0.68091435 | AS56: 0.90677083 | AT56: 0.6875 | AU56: 0.97916667 | AV56: FCCAT - LAFC - CATERING | AY56: 0.5 | AZ56: O-16:35:25 / I-17:05:39 | BA56: 12/16/2025 - PALCALA | BD56: FCBSRV | BE56: CATERING SERVER | BG56: 0 | BH56: 0 | BJ56: 0
A57: FCCAT | B57: FCCAT | C57: 100030897 | D57: HERNANDEZ, JESUS E | E57: PT | F57: F25S39 | G57: 3252 END OF YEAR CELEBRATION - CATERING | H57: 0.6875 | I57: BS | J57: CATERING SERVER | K57: FCCAT23 | L57: FCCAT | M57: BSCAT | N57: 46005 | O57: Sunday | P57: Yes | Q57: 0.58988426 | R57: 0.89319444 | S57: 22 | T57: 1 | U57: FC0030 | V57: 6.78 | W57: 6.78 | AH57: 149.16 | AP57: 149.16 | AR57: 0.58988426 | AS57: 0.89319444 | AT57: 0.60416667 | AU57: 0.89583333 | AV57: FCCAT - LAFC - CATERING | AY57: 0.5 | AZ57: O-15:12:31 / I-15:42:35 | BA57: 12/16/2025 - PALCALA | BD57: FCBSRV | BE57: CATERING SERVER | BG57: 0 | BH57: 0 | BJ57: 0
A58: FCCAT | B58: FCCAT | C58: 100030897 | D58: HERNANDEZ, JESUS E | E58: PT | F58: F25S40 | G58: HEAD COACH PRESS CONFERENCE - CATERING | H58: 0.47916667 | I58: BS | J58: CATERING SERVER | K58: FCCAT21 | L58: FCCAT | M58: BSCAT | N58: 46006 | O58: Monday | P58: No | Q58: 0.28489583 | R58: 0.60583333 | S58: 22 | T58: 1 | U58: FC0030 | V58: 7.2 | W58: 7.2 | AH58: 158.4 | AP58: 158.4 | AR58: 0.28489583 | AS58: 0.60583333 | AT58: 0.29166667 | AU58: 0.625 | AV58: FCCAT - LAFC - CATERING | AY58: 0.5 | AZ58: O-10:21:12 / I-10:51:29 | BA58: 12/16/2025 - PALCALA | BD58: FCBSRV | BE58: CATERING SERVER | BG58: 0 | BH58: 0 | BJ58: 0
A59: FCCON | B59: FCCAT | C59: 100032283 | D59: CASTILLO, DEMICA L | E59: PT | F59: F25C00 | G59: BEECAN HOLIDAY PARTY - CATERING | H59: 0.79166667 | I59: BS | J59: EXTRA CATERING SERVER | K59: FCCAT36 | L59: FCCAT | M59: BSCAT | N59: 46002 | O59: Thursday | P59: No | Q59: 0.70168981 | R59: 0.00027777778 | S59: 22 | T59: 1 | U59: FC0030 | V59: 6.67 | W59: 6.67 | AH59: 146.74 | AP59: 146.74 | AR59: 0.70168981 | AS59: 0.00027777778 | AT59: 0.70833333 | AU59: 1 | AV59: FCCON - | AY59: 0.5 | AZ59: O-16:58:02 / I-17:28:41 | BA59: 12/16/2025 - PALCALA | BD59: FCBSRV | BE59: CATERING SERVER | BF59: CATERING SERVER RATE | BG59: 0 | BH59: 0 | BJ59: 0
A60: FCBAR | B60: FCCAT | C60: 100032345 | D60: JUNIEL, MONIQUE Y | E60: PT | F60: F25C00 | G60: BEECAN HOLIDAY PARTY - CATERING | H60: 0.79166667 | I60: BS | J60: CATERING BARTENDER | K60: FCCATB12 | L60: FCCAT | M60: BSCAT | N60: 46002 | O60: Thursday | P60: No | Q60: 0.68328704 | R60: 0.98268519 | S60: 22 | T60: 1 | U60: FC020 | V60: 6.69 | W60: 6.69 | AE60: 160 | AH60: 147.18 | AP60: 307.18 | AR60: 0.68328704 | AS60: 0.98268519 | AT60: 0.6875 | AU60: 0.020833333 | AV60: FCBAR - | AY60: 0.5 | AZ60: O-16:24:40 / I-17:11:47 | BA60: 12/15/2025 - PALCALA | BD60: FCBART | BE60: CATERING BARTENDER | BF60: FIRST MEAL MANUALLY RECORDED | BG60: 0 | BH60: 0 | BJ60: 0
A61: FCCAT | B61: FCCAT | C61: 100035605 | D61: GODOY, DENISE A | E61: PT | F61: FDAILY | G61: DAILY WORK - LAFC | H61: 0.33333333 | I61: BC | J61: CATERIND LEAD | K61: FCCATLD6 | L61: FCCAT | M61: BSCAT | N61: 45992 | O61: Monday | P61: No | Q61: 0.41090278 | R61: 0.65983796 | S61: 22.5 | T61: 1 | U61: FC0035 | V61: 5.97 | W61: 5.97 | AH61: 134.33 | AP61: 134.33 | AR61: 0.41090278 | AS61: 0.65983796 | AT61: 0.41666667 | AU61: 0.66666667 | AV61: FCCAT - LAFC - CATERING | BA61: 12/02/2025 - PALCALA | BD61: FCLEAD | BE61: CATERING LEAD | BG61: 0 | BH61: 0 | BJ61: 0
A62: FCCAT | B62: FCCAT | C62: 100035605 | D62: GODOY, DENISE A | E62: PT | F62: F25C95 | G62: GLORIA TREVI PRESS EVENT - CATERING | H62: 0.66666667 | I62: BS | J62: CATERIND LEAD | K62: FCCATLD8 | L62: FCCAT | M62: BSCAT | N62: 45993 | O62: Tuesday | P62: No | Q62: 0.28871528 | R62: 0.63513889 | S62: 22.5 | T62: 1 | U62: FC0035 | V62: 7.81 | W62: 7.81 | AH62: 175.73 | AP62: 175.73 | AR62: 0.28871528 | AS62: 0.63513889 | AT62: 0.29166667 | AU62: 0.625 | AV62: FCCAT - LAFC - CATERING | AY62: 0.5 | AZ62: O-08:45:13 / I-09:15:19 | BA62: 12/03/2025 - PALCALA | BD62: FCLEAD | BE62: CATERING LEAD | BG62: 0 | BH62: 0 | BJ62: 0
A63: FCCAT | B63: FCCAT | C63: 100035605 | D63: GODOY, DENISE A | E63: PT | F63: F25C96 | G63: ABM HOLIDAY DINNER - CATERING | H63: 0.70833333 | I63: BS | J63: CATERIND LEAD | K63: FCCATLD6 | L63: FCCAT | M63: BSCAT | N63: 45994 | O63: Wednesday | P63: No | Q63: 0.58082176 | R63: 0.89604167 | S63: 22.5 | T63: 1 | U63: FC0035 | V63: 7.07 | W63: 7.07 | AH63: 159.08 | AP63: 159.08 | AR63: 0.58082176 | AS63: 0.89604167 | AT63: 0.58333333 | AU63: 0.875 | AV63: FCCAT - LAFC - CATERING | AY63: 0.5 | AZ63: O-15:16:08 / I-15:46:47 | BA63: 12/08/2025 - PALCALA | BD63: FCLEAD | BE63: CATERING LEAD | BG63: 0 | BH63: 0 | BJ63: 0
A64: FCCAT | B64: FCCAT | C64: 100035605 | D64: GODOY, DENISE A | E64: PT | F64: F25C97 | G64: FINNISH MOBILITY SHOWCASE - CATERING | H64: 0.70833333 | I64: BS | J64: CATERIND LEAD | K64: FCCATLD5 | L64: FCCAT | M64: BSCAT | N64: 45995 | O64: Thursday | P64: No | Q64: 0.53952546 | R64: 0.85344907 | S64: 22.5 | T64: 1 | U64: FC0035 | V64: 7.03 | W64: 7.03 | AH64: 158.18 | AP64: 158.18 | AR64: 0.53952546 | AS64: 0.85344907 | AT64: 0.54166667 | AU64: 0.85416667 | AV64: FCCAT - LAFC - CATERING | AY64: 0.5 | AZ64: O-15:11:34 / I-15:42:12 | BA64: 12/08/2025 - PALCALA | BD64: FCLEAD | BE64: CATERING LEAD | BG64: 0 | BH64: 0 | BJ64: 0
A65: FCCAT | B65: FCCAT | C65: 100035605 | D65: GODOY, DENISE A | E65: PT | F65: FDAILY | G65: DAILY WORK - LAFC | H65: 0.33333333 | I65: BC | J65: CATERIND LEAD | K65: FCCATLD7 | L65: FCCAT | M65: BSCAT | N65: 45998 | O65: Sunday | P65: Yes | Q65: 0.368125 | R65: 0.61740741 | S65: 22.5 | T65: 1 | U65: FC0035 | V65: 5.98 | W65: 5.98 | AH65: 134.55 | AP65: 134.55 | AR65: 0.368125 | AS65: 0.61740741 | AT65: 0.375 | AU65: 0.625 | AV65: FCCAT - LAFC - CATERING | BA65: 12/08/2025 - PALCALA | BD65: FCLEAD | BE65: CATERING LEAD | BG65: 0 | BH65: 0 | BJ65: 0
A66: FCCAT | B66: FCCAT | C66: 100035605 | D66: GODOY, DENISE A | E66: PT | F66: F25C98 | G66: LA CLEANTECH INCUBATOR DAY 1 - CATERING | H66: 0.66666667 | I66: BS | J66: CATERIND LEAD | K66: FCCATLD8 | L66: FCCAT | M66: BSCAT | N66: 45999 | O66: Monday | P66: No | Q66: 0.30892361 | R66: 0.85650463 | S66: 22.5 | T66: 1 | U66: FC0035 | V66: 13.64 | W66: 8 | X66: 4 | Y66: 0.64 | AA66: 1 | AH66: 180 | AI66: 135 | AJ66: 28.8 | AL66: 22.5 | AP66: 366.3 | AR66: 0.30892361 | AS66: 0.85650463 | AT66: 0.3125 | AU66: 0.85416667 | AV66: FCCAT - LAFC - CATERING | AY66: 0.5 | AZ66: O-10:51:29 / I-11:21:49 | BA66: 12/10/2025 - PALCALA | BD66: FCLEAD | BE66: CATERING LEAD | BF66: MEAL PREMIUM/SECOND LUNCH | BG66: 0 | BH66: 0 | BJ66: 0
A67: FCCAT | B67: FCCAT | C67: 100035605 | D67: GODOY, DENISE A | E67: PT | F67: F25C99 | G67: LA CLEANTECH INCUBATOR - DAY 2 - CATERING | H67: 0.375 | I67: BS | J67: CATERIND LEAD | K67: FCCATLD6 | L67: FCCAT | M67: BSCAT | N67: 46000 | O67: Tuesday | P67: No | Q67: 0.29090278 | R67: 0.75707176 | S67: 22.5 | T67: 1 | U67: FC0035 | V67: 10.69 | W67: 8 | X67: 2.69 | AH67: 180 | AI67: 90.79 | AP67: 270.79 | AR67: 0.29090278 | AS67: 0.75707176 | AT67: 0.29166667 | AU67: 0.625 | AV67: FCCAT - LAFC - CATERING | AY67: 0.5 | AZ67: O-10:39:06 / I-11:10:01 | BA67: 12/10/2025 - PALCALA | BD67: FCLEAD | BE67: CATERING LEAD | BG67: 0 | BH67: 0 | BJ67: 0
A68: FCCAT | B68: FCCAT | C68: 100035605 | D68: GODOY, DENISE A | E68: PT | F68: FDAILY | G68: DAILY WORK - LAFC | H68: 0.33333333 | I68: BC | J68: CATERIND LEAD | K68: FCCATLD6 | L68: FCCAT | M68: BSCAT | N68: 46001 | O68: Wednesday | P68: No | Q68: 0.57638889 | R68: 0.76388889 | S68: 22.5 | T68: 1 | U68: FC0035 | V68: 4.5 | W68: 4.5 | AH68: 101.25 | AP68: 101.25 | AT68: 0.5 | AU68: 0.75 | AV68: FCCAT - LAFC - CATERING | BA68: 12/15/2025 - PALCALA | BD68: FCLEAD | BE68: CATERING LEAD | BF68: IN AND OUT PUNCH/FIRST MEAL MANUALLY RECORDED | BG68: 0 | BH68: 0 | BJ68: 0
A69: FCCAT | B69: FCCAT | C69: 100035605 | D69: GODOY, DENISE A | E69: PT | F69: F25C00 | G69: BEECAN HOLIDAY PARTY - CATERING | H69: 0.79166667 | I69: BS | J69: CATERIND LEAD | K69: FCCATLD7 | L69: FCCAT | M69: BSCAT | N69: 46002 | O69: Thursday | P69: No | Q69: 0.65984954 | R69: 0.014097222 | S69: 22.5 | T69: 1 | U69: FC0035 | V69: 8 | W69: 8 | AH69: 180 | AP69: 180 | AR69: 0.65984954 | AS69: 0.014097222 | AT69: 0.66666667 | AU69: 1 | AV69: FCCAT - LAFC - CATERING | AY69: 0.5 | AZ69: O-17:04:35 / I-17:35:01 | BA69: 12/16/2025 - PALCALA | BD69: FCLEAD | BE69: CATERING LEAD | BG69: 0 | BH69: 0 | BJ69: 0
A70: FCCAT | B70: FCCAT | C70: 100035605 | D70: GODOY, DENISE A | E70: PT | F70: F25C24 | G70: FISHER PHILLIPS HOLIDAY PARTY - CATERING | H70: 0.79166667 | I70: BS | J70: CATERIND LEAD | K70: FCCATLD8 | L70: FCCAT | M70: BSCAT | N70: 46003 | O70: Friday | P70: No | Q70: 0.57648148 | R70: 0.99109954 | S70: 22.5 | T70: 1 | U70: FC0035 | V70: 9.45 | W70: 8 | X70: 1.45 | AH70: 180 | AI70: 48.94 | AP70: 228.94 | AR70: 0.57648148 | AS70: 0.99109954 | AT70: 0.58333333 | AU70: 0.97916667 | AV70: FCCAT - LAFC - CATERING | AY70: 0.5 | AZ70: O-15:51:31 / I-16:21:53 | BA70: 12/16/2025 - PALCALA | BD70: FCLEAD | BE70: CATERING LEAD | BG70: 0 | BH70: 0 | BJ70: 0
A71: FCCAT | B71: FCCAT | C71: 100035605 | D71: GODOY, DENISE A | E71: PT | F71: F25S39 | G71: 3252 END OF YEAR CELEBRATION - CATERING | H71: 0.6875 | I71: BS | J71: CATERIND LEAD | K71: FCCATLD5 | L71: FCCAT | M71: BSCAT | N71: 46005 | O71: Sunday | P71: Yes | Q71: 0.5809375 | R71: 0.90462963 | S71: 22.5 | T71: 1 | U71: FC0035 | V71: 7.18 | W71: 7.18 | AH71: 161.55 | AP71: 161.55 | AR71: 0.5809375 | AS71: 0.90462963 | AT71: 0.58333333 | AU71: 0.89583333 | AV71: FCCAT - LAFC - CATERING | AY71: 0.59 | AZ71: O-15:37:47 / I-16:13:23 | BA71: 12/16/2025 - PALCALA | BD71: FCLEAD | BE71: CATERING LEAD | BG71: 0 | BH71: 0 | BJ71: 0
A72: FCCAT | B72: FCCAT | C72: 100035605 | D72: GODOY, DENISE A | E72: PT | F72: F25S40 | G72: HEAD COACH PRESS CONFERENCE - CATERING | H72: 0.47916667 | I72: BS | J72: CATERIND LEAD | K72: FCCATLD6 | L72: FCCAT | M72: BSCAT | N72: 46006 | O72: Monday | P72: No | Q72: 0.2930787 | R72: 0.62371528 | S72: 22.5 | T72: 1 | U72: FC0035 | V72: 7.44 | W72: 7.44 | AH72: 167.4 | AP72: 167.4 | AR72: 0.2930787 | AS72: 0.62371528 | AT72: 0.29166667 | AU72: 0.625 | AV72: FCCAT - LAFC - CATERING | AY72: 0.5 | AZ72: O-11:02:08 / I-11:32:34 | BA72: 12/16/2025 - PALCALA | BD72: FCLEAD | BE72: CATERING LEAD | BG72: 0 | BH72: 0 | BJ72: 0
A73: FCCAT | B73: FCCAT | C73: 100035605 | D73: GODOY, DENISE A | E73: PT | F73: FDAILY | G73: DAILY WORK - LAFC | H73: 0.33333333 | I73: BC | J73: CATERIND LEAD | K73: FCCATLD6 | L73: FCCAT | M73: BSCAT | N73: 46007 | O73: Tuesday | P73: No | Q73: 0.41025463 | R73: 0.71766204 | S73: 22.5 | T73: 1 | U73: FC0035 | V73: 6.88 | W73: 4.88 | X73: 2 | AH73: 109.8 | AI73: 67.5 | AP73: 177.3 | AR73: 0.41025463 | AS73: 0.71766204 | AT73: 0.41666667 | AU73: 0.70833333 | AV73: FCCAT - LAFC - CATERING | AY73: 0.5 | AZ73: O-12:35:12 / I-13:05:32 | BA73: 12/17/2025 - PALCALA | BD73: FCLEAD | BE73: CATERING LEAD | BG73: 0 | BH73: 0 | BJ73: 0
A74: FCBAR | B74: FCCAT | C74: 100036211 | D74: CHAIREZ, RICARDO | E74: PT | F74: F25C95 | G74: GLORIA TREVI PRESS EVENT - CATERING | H74: 0.66666667 | I74: BS | J74: CATERING BARTENDER | K74: FCCATB51 | L74: FCCAT | M74: BSCAT | N74: 45993 | O74: Tuesday | P74: No | Q74: 0.34388889 | R74: 0.5962963 | S74: 22 | T74: 1 | U74: FC0030 | V74: 7.06 | W74: 6.06 | AA74: 1 | AE74: 175 | AH74: 133.32 | AL74: 20.61 | AP74: 328.93 | AQ74: Yes | AR74: 0.34388889 | AS74: 0.5962963 | AT74: 0.33333333 | AU74: 0.625 | AV74: FCBAR - | BA74: 12/03/2025 - PALCALA | BD74: FCBART | BE74: CATERING BARTENDER | BF74: PAY TYPE ADJUSTED MEAL PREMIUM | BG74: 0 | BH74: 0 | BJ74: 0
A75: FCBAR | B75: FCCAT | C75: 100036211 | D75: CHAIREZ, RICARDO | E75: PT | F75: FDAILY | G75: DAILY WORK - LAFC | H75: 0.33333333 | I75: BC | J75: CATERING BARTENDER | K75: FCCATB09 | L75: FCCAT | M75: BSCAT | N75: 46001 | O75: Wednesday | P75: No | Q75: 0.50163194 | R75: 0.7106713 | S75: 18.25 | T75: 1 | U75: FB0035 | V75: 5.02 | W75: 5.02 | AH75: 91.62 | AP75: 91.62 | AR75: 0.50163194 | AS75: 0.7106713 | AT75: 0.5 | AU75: 0.70833333 | AV75: FCBAR - | BA75: 12/15/2025 - PALCALA | BD75: FCBART | BE75: CATERING BARTENDER | BG75: 0 | BH75: 0 | BJ75: 0
A76: FCBAR | B76: FCCAT | C76: 100036211 | D76: CHAIREZ, RICARDO | E76: PT | F76: F25C00 | G76: BEECAN HOLIDAY PARTY - CATERING | H76: 0.79166667 | I76: BS | J76: CATERING BARTENDER | K76: FCCATB03 | L76: FCCAT | M76: BSCAT | N76: 46002 | O76: Thursday | P76: No | Q76: 0.68239583 | R76: 0.9949537 | S76: 22 | T76: 1 | U76: FC020 | V76: 7 | W76: 7 | AE76: 150 | AH76: 154 | AP76: 304 | AR76: 0.68239583 | AS76: 0.9949537 | AT76: 0.6875 | AU76: 0.020833333 | AV76: FCBAR - | AY76: 0.5 | AZ76: O-16:38:09 | BA76: 12/15/2025 - PALCALA | BD76: FCBART | BE76: CATERING BARTENDER | BF76: FIRST MEAL MANUALLY RECORDED | BG76: 0 | BH76: 0 | BJ76: 0
A77: FCBAR | B77: FCCAT | C77: 100036438 | D77: PALAFOX, LUIS R | E77: PT | F77: F25C00 | G77: BEECAN HOLIDAY PARTY - CATERING | H77: 0.79166667 | I77: BS | J77: CATERING BARTENDER | K77: FCCATB08 | L77: FCCAT | M77: BSCAT | N77: 46002 | O77: Thursday | P77: No | Q77: 0.68105324 | R77: 0.98658565 | S77: 22 | T77: 1 | U77: FC020 | V77: 6.74 | W77: 6.74 | AE77: 175 | AH77: 148.28 | AP77: 323.28 | AR77: 0.68105324 | AS77: 0.98658565 | AT77: 0.6875 | AU77: 0.020833333 | AV77: FCBAR - | AY77: 0.6 | AZ77: O-16:31:35 / I-17:07:17 | BA77: 12/15/2025 - PALCALA | BD77: FCBART | BE77: CATERING BARTENDER | BG77: 0 | BH77: 0 | BJ77: 0
A78: FCBAR | B78: FCCAT | C78: 100036537 | D78: SILIEZAR, EDUARDO | E78: PT | F78: F25C00 | G78: BEECAN HOLIDAY PARTY - CATERING | H78: 0.79166667 | I78: BS | J78: BAR SUPERVISOR | K78: FCBARSP1 | L78: FCCAT | M78: FCCAT100 | N78: 46002 | O78: Thursday | P78: No | Q78: 0.65991898 | R78: 0.002662037 | S78: 23 | T78: H | U78: FB0040 | V78: 7.73 | W78: 7.73 | AH78: 177.79 | AP78: 177.79 | AR78: 0.65991898 | AS78: 0.002662037 | AT78: 0.66666667 | AU78: 0.020833333 | AV78: FCBAR - | AY78: 0.5 | BA78: 12/15/2025 - PALCALA | BD78: FCBSUP | BE78: CATERING SUPERVISOR | BF78: FIRST MEAL MANUALLY RECORDED | BG78: 0 | BH78: 0 | BJ78: 0
A79: FCBAR | B79: FCCAT | C79: 100036537 | D79: SILIEZAR, EDUARDO | E79: PT | F79: F25C24 | G79: FISHER PHILLIPS HOLIDAY PARTY - CATERING | H79: 0.79166667 | I79: BS | J79: BAR SUPERVISOR | K79: FCBARSP4 | L79: FCCAT | N79: 46003 | O79: Friday | P79: No | Q79: 0.66047454 | R79: 0.98607639 | S79: 23 | T79: H | U79: FB0040 | V79: 7.31 | W79: 7.31 | AH79: 168.13 | AP79: 168.13 | AR79: 0.66047454 | AS79: 0.98607639 | AT79: 0.66666667 | AU79: 0.97916667 | AV79: FCBAR - | AY79: 0.5 | BA79: 12/15/2025 - PALCALA | BD79: FCBSUP | BE79: CATERING SUPERVISOR | BF79: FIRST MEAL MANUALLY RECORDED | BG79: 0 | BH79: 0 | BJ79: 0
A80: FCBAR | B80: FCCAT | C80: 100039076 | D80: ZARLENGO, THERESE | E80: PT | F80: F25C24 | G80: FISHER PHILLIPS HOLIDAY PARTY - CATERING | H80: 0.79166667 | I80: BS | J80: CATERING BARTENDER | K80: FCCATB09 | L80: FCCAT | M80: BSCAT | N80: 46003 | O80: Friday | P80: No | Q80: 0.68283565 | R80: 0.97537037 | S80: 18.25 | T80: 1 | U80: FB0035 | V80: 6.52 | W80: 6.52 | AE80: 155 | AH80: 118.99 | AP80: 273.99 | AR80: 0.68283565 | AS80: 0.97537037 | AT80: 0.6875 | AU80: 0.97916667 | AV80: FCBAR - | AY80: 0.5 | BA80: 12/15/2025 - PALCALA | BD80: FCBART | BE80: CATERING BARTENDER | BF80: FIRST MEAL MANUALLY RECORDED | BG80: 0 | BH80: 0 | BJ80: 0
A81: FCBAR | B81: FCCAT | C81: 100039079 | D81: SADRI, MICHAEL | E81: PT | F81: F25C00 | G81: BEECAN HOLIDAY PARTY - CATERING | H81: 0.79166667 | I81: BS | J81: CATERING BARTENDER | K81: FCCATB17 | L81: FCCAT | M81: BSCAT | N81: 46002 | O81: Thursday | P81: No | Q81: 0.68914352 | R81: 0.98724537 | S81: 22 | T81: 1 | U81: FC020 | V81: 6.65 | W81: 6.65 | AE81: 175 | AH81: 146.3 | AP81: 321.3 | AR81: 0.68914352 | AS81: 0.98724537 | AT81: 0.6875 | AU81: 1 | AV81: FCBAR - | AY81: 0.5 | AZ81: O-16:46:21 / I-17:16:52 | BA81: 12/15/2025 - PALCALA | BD81: FCBART | BE81: CATERING BARTENDER | BG81: 0 | BH81: 0 | BJ81: 0
A82: FCBAR | B82: FCCAT | C82: 100039090 | D82: LEWIS, CRISTAL | E82: PT | F82: F25C95 | G82: GLORIA TREVI PRESS EVENT - CATERING | H82: 0.66666667 | I82: BS | J82: CATERING BARTENDER | K82: FCCATB50 | L82: FCCAT | M82: BSCAT | N82: 45993 | O82: Tuesday | P82: No | Q82: 0.33402778 | R82: 0.62381944 | S82: 22 | T82: 1 | U82: FC020 | V82: 6.46 | W82: 6.46 | AE82: 175 | AH82: 142.12 | AP82: 317.12 | AR82: 0.33402778 | AS82: 0.62381944 | AT82: 0.33333333 | AU82: 0.625 | AV82: FCBAR - | AY82: 0.5 | AZ82: O-09:08:38 / I-09:39:51 | BA82: 12/03/2025 - PALCALA | BD82: FCBART | BE82: CATERING BARTENDER | BG82: 0 | BH82: 0 | BJ82: 0
A83: FCBAR | B83: FCCAT | C83: 100039090 | D83: LEWIS, CRISTAL | E83: PT | F83: F25C96 | G83: ABM HOLIDAY DINNER - CATERING | H83: 0.70833333 | I83: BS | J83: CATERING BARTENDER | K83: FCCATB01 | L83: FCCAT | M83: BSCAT | N83: 45994 | O83: Wednesday | P83: No | Q83: 0.62386574 | R83: 0.86831019 | S83: 22 | T83: 1 | U83: FC020 | V83: 5.87 | W83: 5.87 | AE83: 175 | AH83: 129.14 | AP83: 304.14 | AR83: 0.62386574 | AS83: 0.86831019 | AT83: 0.625 | AU83: 0.89583333 | AV83: FCBAR - | BA83: 12/08/2025 - PALCALA | BD83: FCBART | BE83: CATERING BARTENDER | BG83: 0 | BH83: 0 | BJ83: 0
A84: FCBAR | B84: FCCAT | C84: 100039090 | D84: LEWIS, CRISTAL | E84: PT | F84: F25C98 | G84: LA CLEANTECH INCUBATOR DAY 1 - CATERING | H84: 0.66666667 | I84: BS | J84: CATERING BARTENDER | K84: FCCATB08 | L84: FCCAT | M84: BSCAT | N84: 45999 | O84: Monday | P84: No | Q84: 0.61826389 | R84: 0.84577546 | S84: 22 | T84: 1 | U84: FC020 | V84: 5.46 | W84: 5.46 | AE84: 175 | AH84: 120.12 | AP84: 295.12 | AR84: 0.61826389 | AS84: 0.84577546 | AT84: 0.625 | AU84: 0.85416667 | AV84: FCBAR - | BA84: 12/09/2025 - PALCALA | BD84: FCBART | BE84: CATERING BARTENDER | BG84: 0 | BH84: 0 | BJ84: 0
A85: FCBAR | B85: FCCAT | C85: 100039090 | D85: LEWIS, CRISTAL | E85: PT | F85: FDAILY | G85: DAILY WORK - LAFC | H85: 0.33333333 | I85: BC | J85: CATERING BARTENDER | K85: FCCATB71 | L85: FCCAT | M85: BSCAT | N85: 46001 | O85: Wednesday | P85: No | Q85: 0.4609375 | R85: 0.67435185 | S85: 22 | T85: 1 | U85: FC020 | V85: 5.12 | W85: 5.12 | AH85: 112.64 | AP85: 112.64 | AR85: 0.4609375 | AS85: 0.67435185 | AT85: 0.5 | AU85: 0.66666667 | AV85: FCBAR - | BA85: 12/15/2025 - PALCALA | BD85: FCBART | BE85: CATERING BARTENDER | BG85: 0 | BH85: 0 | BJ85: 0
A86: FCBAR | B86: FCCAT | C86: 100039090 | D86: LEWIS, CRISTAL | E86: PT | F86: F25C00 | G86: BEECAN HOLIDAY PARTY - CATERING | H86: 0.79166667 | I86: BS | J86: CATERING BARTENDER | K86: FCCATB01 | L86: FCCAT | M86: BSCAT | N86: 46002 | O86: Thursday | P86: No | Q86: 0.68334491 | R86: 0.98277778 | S86: 22 | T86: 1 | U86: FC020 | V86: 6.69 | W86: 6.69 | AE86: 160 | AH86: 147.18 | AP86: 307.18 | AR86: 0.68334491 | AS86: 0.98277778 | AT86: 0.6875 | AU86: 0.020833333 | AV86: FCBAR - | AY86: 0.5 | AZ86: O-16:24:48 | BA86: 12/15/2025 - PALCALA | BD86: FCBART | BE86: CATERING BARTENDER | BF86: FIRST MEAL MANUALLY RECORDED | BG86: 0 | BH86: 0 | BJ86: 0
A87: FCBAR | B87: FCCAT | C87: 100039090 | D87: LEWIS, CRISTAL | E87: PT | F87: F25C24 | G87: FISHER PHILLIPS HOLIDAY PARTY - CATERING | H87: 0.79166667 | I87: BS | J87: CATERING BARTENDER | K87: FCCATB07 | L87: FCCAT | M87: BSCAT | N87: 46003 | O87: Friday | P87: No | Q87: 0.68180556 | R87: 0.96925926 | S87: 22 | T87: 1 | U87: FC020 | V87: 6.4 | W87: 6.4 | AE87: 175 | AH87: 140.8 | AP87: 315.8 | AR87: 0.68180556 | AS87: 0.96925926 | AT87: 0.6875 | AU87: 0.97916667 | AV87: FCBAR - | AY87: 0.5 | BA87: 12/15/2025 - PALCALA | BD87: FCBART | BE87: CATERING BARTENDER | BF87: FIRST MEAL MANUALLY RECORDED | BG87: 0 | BH87: 0 | BJ87: 0
A88: FCCAT | B88: FCCAT | C88: 100039107 | D88: ESPINOZA, REINA I | E88: PT | F88: F25C98 | G88: LA CLEANTECH INCUBATOR DAY 1 - CATERING | H88: 0.66666667 | I88: BS | J88: CATERING SERVER | K88: FCCAT26 | L88: FCCAT | M88: BSCAT | N88: 45999 | O88: Monday | P88: No | Q88: 0.49363426 | R88: 0.84258102 | S88: 22 | T88: 1 | U88: FC0030 | V88: 7.87 | W88: 7.87 | AH88: 173.14 | AP88: 173.14 | AR88: 0.49363426 | AS88: 0.84258102 | AT88: 0.5 | AU88: 0.85416667 | AV88: FCCAT - LAFC - CATERING | AY88: 0.5 | AZ88: O-14:09:58 / I-14:40:21 | BA88: 12/10/2025 - PALCALA | BD88: FCBSRV | BE88: CATERING SERVER | BG88: 0 | BH88: 0 | BJ88: 0
A89: FCCAT | B89: FCCAT | C89: 100039107 | D89: ESPINOZA, REINA I | E89: PT | F89: F25C99 | G89: LA CLEANTECH INCUBATOR - DAY 2 - CATERING | H89: 0.375 | I89: BS | J89: CATERING SERVER | K89: FCCAT27 | L89: FCCAT | M89: BSCAT | N89: 46000 | O89: Tuesday | P89: No | Q89: 0.45168981 | R89: 0.7503125 | S89: 22 | T89: 1 | U89: FC0030 | V89: 6.67 | W89: 6.67 | AH89: 146.74 | AP89: 146.74 | AR89: 0.45168981 | AS89: 0.7503125 | AT89: 0.45833333 | AU89: 0.75 | AV89: FCCAT - LAFC - CATERING | AY89: 0.5 | AZ89: O-14:56:11 / I-15:27:09 | BA89: 12/10/2025 - PALCALA | BD89: FCBSRV | BE89: CATERING SERVER | BG89: 0 | BH89: 0 | BJ89: 0
A90: FCCAT | B90: FCCAT | C90: 100039107 | D90: ESPINOZA, REINA I | E90: PT | F90: F25C00 | G90: BEECAN HOLIDAY PARTY - CATERING | H90: 0.79166667 | I90: BS | J90: CATERING SERVER | K90: FCCAT33 | L90: FCCAT | M90: BSCAT | N90: 46002 | O90: Thursday | P90: No | Q90: 0.73428241 | R90: 0.99127315 | S90: 22 | T90: 1 | U90: FC0030 | V90: 7.17 | W90: 6.17 | AA90: 1 | AH90: 135.74 | AL90: 22 | AP90: 157.74 | AR90: 0.73428241 | AS90: 0.99127315 | AT90: 0.72916667 | AU90: 1 | AV90: FCCAT - LAFC - CATERING | BA90: 12/16/2025 - PALCALA | BD90: FCBSRV | BE90: CATERING SERVER | BF90: MEAL PREMIUM | BG90: 0 | BH90: 0 | BJ90: 0
A91: FCCAT | B91: FCCAT | C91: 100039237 | D91: DIAZ, JORGE | E91: PT | F91: F25C95 | G91: GLORIA TREVI PRESS EVENT - CATERING | H91: 0.66666667 | I91: BS | J91: CATERING SERVER | K91: FCCAT23 | L91: FCCAT | M91: BSCAT | N91: 45993 | O91: Tuesday | P91: No | Q91: 0.29166667 | R91: 0.60416667 | S91: 22 | T91: 1 | U91: FC0030 | V91: 7 | W91: 7 | AH91: 154 | AP91: 154 | AT91: 0.29166667 | AU91: 0.625 | AV91: FCCAT - LAFC - CATERING | AY91: 0.5 | BA91: 12/03/2025 - PALCALA | BD91: FCBSRV | BE91: CATERING SERVER | BF91: IN AND OUT PUNCH/FIRST MEAL MANUALLY RECORDED | BG91: 0 | BH91: 0 | BJ91: 0
A92: FCCAT | B92: FCCAT | C92: 100039237 | D92: DIAZ, JORGE | E92: PT | F92: F25C96 | G92: ABM HOLIDAY DINNER - CATERING | H92: 0.70833333 | I92: BS | J92: CATERING SERVER | K92: FCCAT72 | L92: FCCAT | M92: BSCAT | N92: 45994 | O92: Wednesday | P92: No | Q92: 0.5769213 | R92: 0.854375 | S92: 22 | T92: 1 | U92: FC0030 | V92: 6.16 | W92: 6.16 | AH92: 135.52 | AP92: 135.52 | AR92: 0.5769213 | AS92: 0.854375 | AT92: 0.58333333 | AU92: 0.85416667 | AV92: FCCAT - LAFC - CATERING | AY92: 0.5 | AZ92: O-15:06:57 / I-15:37:23 | BA92: 12/08/2025 - PALCALA | BD92: FCBSRV | BE92: CATERING SERVER | BG92: 0 | BH92: 0 | BJ92: 0
A93: FCCAT | B93: FCCAT | C93: 100039237 | D93: DIAZ, JORGE | E93: PT | F93: F25C98 | G93: LA CLEANTECH INCUBATOR DAY 1 - CATERING | H93: 0.66666667 | I93: BS | J93: CATERING SERVER | K93: FCCAT25 | L93: FCCAT | M93: BSCAT | N93: 45999 | O93: Monday | P93: No | Q93: 0.49341435 | R93: 0.83539352 | S93: 22 | T93: 1 | U93: FC0030 | V93: 7.71 | W93: 7.71 | AH93: 169.62 | AP93: 169.62 | AR93: 0.49341435 | AS93: 0.83539352 | AT93: 0.5 | AU93: 0.85416667 | AV93: FCCAT - LAFC - CATERING | AY93: 0.5 | AZ93: O-14:07:49 / I-14:38:26 | BA93: 12/10/2025 - PALCALA | BD93: FCBSRV | BE93: CATERING SERVER | BG93: 0 | BH93: 0 | BJ93: 0
A94: FCCAT | B94: FCCAT | C94: 100039237 | D94: DIAZ, JORGE | E94: PT | F94: F25C00 | G94: BEECAN HOLIDAY PARTY - CATERING | H94: 0.79166667 | I94: BS | J94: CATERING SERVER | K94: FCCAT32 | L94: FCCAT | M94: BSCAT | N94: 46002 | O94: Thursday | P94: No | Q94: 0.70178241 | R94: 0.99181713 | S94: 22 | T94: 1 | U94: FC0030 | V94: 6.46 | W94: 6.46 | AH94: 142.12 | AP94: 142.12 | AR94: 0.70178241 | AS94: 0.99181713 | AT94: 0.70833333 | AU94: 1 | AV94: FCCAT - LAFC - CATERING | AY94: 0.5 | AZ94: O-17:00:03 / I-17:30:15 | BA94: 12/16/2025 - PALCALA | BD94: FCBSRV | BE94: CATERING SERVER | BG94: 0 | BH94: 0 | BJ94: 0
A95: FCINS | B95: FCCAT | C95: 100041219 | D95: TORRES, BLANCA E | E95: PT | F95: F25C00 | G95: BEECAN HOLIDAY PARTY - CATERING | H95: 0.79166667 | I95: BS | J95: CATERING SERVER | K95: FCCAT25 | L95: FCCAT | M95: BSCAT | N95: 46002 | O95: Thursday | P95: No | Q95: 0.70288194 | R95: 0.00025462963 | S95: 22 | T95: 1 | U95: FC0030 | V95: 6.55 | W95: 6.55 | AH95: 144.1 | AP95: 144.1 | AR95: 0.70288194 | AS95: 0.00025462963 | AT95: 0.70833333 | AU95: 1 | AV95: FCINS - | AY95: 0.59 | AZ95: O-16:53:22 / I-17:28:37 | BA95: 12/16/2025 - PALCALA | BD95: FCBSRV | BE95: CATERING SERVER | BG95: 0 | BH95: 0 | BJ95: 0
A96: FCCAT | B96: FCCAT | C96: 100044773 | D96: BOREN, ADAM | E96: PT | F96: F25C98 | G96: LA CLEANTECH INCUBATOR DAY 1 - CATERING | H96: 0.66666667 | I96: BS | J96: CATERING SERVER | K96: FCCAT27 | L96: FCCAT | M96: BSCAT | N96: 45999 | O96: Monday | P96: No | Q96: 0.49799769 | R96: 0.84704861 | S96: 22 | T96: 1 | U96: FC0030 | V96: 7.88 | W96: 7.88 | AH96: 173.36 | AP96: 173.36 | AR96: 0.49799769 | AS96: 0.84704861 | AT96: 0.5 | AU96: 0.85416667 | AV96: FCCAT - LAFC - CATERING | AY96: 0.5 | AZ96: O-14:11:30 / I-14:43:51 | BA96: 12/10/2025 - PALCALA | BD96: FCBSRV | BE96: CATERING SERVER | BG96: 0 | BH96: 0 | BJ96: 0
A97: FCBAR | B97: FCCAT | C97: 100047474 | D97: HATCHER, LACONIA | E97: PT | F97: F25C97 | G97: FINNISH MOBILITY SHOWCASE - CATERING | H97: 0.70833333 | I97: BS | J97: CATERING BARTENDER | K97: FCCATB05 | L97: FCCAT | M97: BSCAT | N97: 45995 | O97: Thursday | P97: No | Q97: 0.61818287 | R97: 0.84050926 | S97: 17.87 | T97: 1 | U97: FB0025 | V97: 4.84 | W97: 4.84 | AE97: 175 | AH97: 86.49 | AP97: 261.49 | AR97: 0.61818287 | AS97: 0.84050926 | AT97: 0.625 | AU97: 0.875 | AV97: FCBAR - | AY97: 0.5 | AZ97: O-15:07:33 / I-15:41:21 | BA97: 12/08/2025 - PALCALA | BD97: FCBART | BE97: CATERING BARTENDER | BG97: 0 | BH97: 0 | BJ97: 0
A98: FCBAR | B98: FCCAT | C98: 100047474 | D98: HATCHER, LACONIA | E98: PT | F98: F25C00 | G98: BEECAN HOLIDAY PARTY - CATERING | H98: 0.79166667 | I98: BS | J98: CATERING BARTENDER | K98: FCCATB19 | L98: FCCAT | M98: BSCAT | N98: 46002 | O98: Thursday | P98: No | Q98: 0.680625 | R98: 0.98291667 | S98: 22 | T98: 1 | U98: FC020 | V98: 6.76 | W98: 6.76 | AE98: 160 | AH98: 148.72 | AP98: 308.72 | AR98: 0.680625 | AS98: 0.98291667 | AT98: 0.6875 | AU98: 1 | AV98: FCBAR - | AY98: 0.5 | AZ98: O-16:50:10 / I-17:20:11 | BA98: 12/15/2025 - PALCALA | BD98: FCBART | BE98: CATERING BARTENDER | BG98: 0 | BH98: 0 | BJ98: 0
A99: FCSTE | B99: FCCAT | C99: 100049312 | D99: GONZALEZ, ANAIS | E99: PT | F99: F25C00 | G99: BEECAN HOLIDAY PARTY - CATERING | H99: 0.79166667 | I99: BS | J99: BAR SUPERVISOR | K99: FCBARSP4 | L99: FCCAT | N99: 46002 | O99: Thursday | P99: No | Q99: 0.625 | S99: 24 | T99: H | U99: FS0056 | V99: 8.5 | W99: 8 | X99: 0.5 | AH99: 192 | AI99: 18 | AP99: 210 | AV99: FCSTE - | AY99: 0.5 | BA99: 12/12/2025 - PALCALA | BD99: FCBSUP | BE99: CATERING SUPERVISOR | BF99: IN AND OUT PUNCH/FIRST MEAL MANUALLY RECORDED | BG99: 0 | BH99: 0 | BJ99: 0
A100: FCCAT | B100: FCCAT | C100: 100049344 | D100: MANCIA, JULIO | E100: PT | F100: F25C96 | G100: ABM HOLIDAY DINNER - CATERING | H100: 0.70833333 | I100: BS | J100: CATERING SERVER | K100: FCCAT73 | L100: FCCAT | M100: BSCAT | N100: 45994 | O100: Wednesday | P100: No | Q100: 0.57737269 | R100: 0.85454861 | S100: 22 | T100: 1 | U100: FC0030 | V100: 6.15 | W100: 6.15 | AH100: 135.3 | AP100: 135.3 | AR100: 0.57737269 | AS100: 0.85454861 | AT100: 0.58333333 | AU100: 0.85416667 | AV100: FCCAT - LAFC - CATERING | AY100: 0.5 | AZ100: O-15:02:43 / I-15:33:00 | BA100: 12/08/2025 - PALCALA | BD100: FCBSRV | BE100: CATERING SERVER | BG100: 0 | BH100: 0 | BJ100: 0
A101: FCCAT | B101: FCCAT | C101: 100049344 | D101: MANCIA, JULIO | E101: PT | F101: F25C98 | G101: LA CLEANTECH INCUBATOR DAY 1 - CATERING | H101: 0.66666667 | I101: BS | J101: CATERING SERVER | K101: FCCAT29 | L101: FCCAT | M101: BSCAT | N101: 45999 | O101: Monday | P101: No | Q101: 0.49334491 | R101: 0.83528935 | S101: 22 | T101: 1 | U101: FC0030 | V101: 7.71 | W101: 7.71 | AH101: 169.62 | AP101: 169.62 | AR101: 0.49334491 | AS101: 0.83528935 | AT101: 0.5 | AU101: 0.85416667 | AV101: FCCAT - LAFC - CATERING | AY101: 0.5 | AZ101: O-14:08:11 / I-14:38:51 | BA101: 12/10/2025 - PALCALA | BD101: FCBSRV | BE101: CATERING SERVER | BG101: 0 | BH101: 0 | BJ101: 0
...

Sheet term
A1: 100047412 | B1: BEBO, STEPHANIE | C1: Active | D1: Server, Catering | E1: 615-28-1335
A2: 100087214 | B2: BESSER III, FRANK L. | C2: Active | D2: Club Attendant | E2: 176-76-8381
A3: 100084264 | B3: Castillo, Christian | C3: Active | D3: Barback, Premium | E3: 606-17-2939
A4: 100074398 | B4: COCOMA, Jayde C. | C4: Active | D4: Warehouse Associate | E4: 578-39-0167
A5: 100084247 | B5: De La Rosa, Gesel | C5: Active | D5: Cashier, Concessions | E5: 626-25-3481
A6: 100087233 | B6: DIXON, KAMESHA S. | C6: Active | D6: Dishwasher | E6: 550-79-8394
A7: 100087231 | B7: Dixon, Tamesha F. | C7: Active | D7: Dishwasher | E7: 550-79-6307
A8: 100054473 | B8: JOHNSON, ALAYAH | C8: Active | D8: Concessions Stand Lead | E8: 626-41-7445
A9: 100054474 | B9: JONES, ERICK | C9: Active | D9: Club Attendant | E9: 604-21-5499
A10: 100062557 | B10: Jonewell, James | C10: Active | D10: Runner, Suites | E10: 104-66-5573
A11: 100074375 | B11: LOPEZ, ESMERALDA | C11: Active | D11: Runner, Suites | E11: 539-25-3879
A12: 100059517 | B12: MAK, Samatha | C12: Active | D12: Bartender, Premium | E12: 462-53-2217
... A32: 100048023 | B32: MENDEZ, BRIAN | C32: Active | D32: Cashier, Concessions | E32: 611-29-3237
A33: 100089106 | B33: Musa, Yahmani | C33: Active | D33: Club Attendant | E33: 603-23-0185
A34: 100060728 | B34: NEGRETE, JAVIER | C34: Active | D34: Dishwasher | E34: 624-58-0770
A35: 100087215 | B35: ORTIZ, VANESSA | C35: Active | D35: Concessions Stand Lead | E35: 555-91-0498
A36: 100087282 | B36: ROYAL, TONIA | C36: Active | D36: Concessions Stand Lead | E36: 458-29-4960
A37: 100030337 | B37: Sanchez, Marina | C37: Active | D37: Server, Catering | E37: 560-45-7252
A38: 100049325 | B38: SERVELLON Jr., ISAI | C38: Active | D38: Concessions Stand Lead | E38: 613-23-7693
A39: 100073366 | B39: Gonzalez Rosas, Abelardo | C39: Active | D39: Cook 3 | E39: 602-33-7921
A40: 100073274 | B40: AMEZOLA, FRED | C40: Active | D40: Cook 3 | E40: 547-77-1250
A41: 100036391 | B41: Sepulveda de Rodarte, Carmen | C41: Active | D41: Cook 2 | E41: 606-53-4186
A42: 100093390 | B42: Cooper, Cornell | C42: Active | D42: Concessions Stand Lead | E42: 554-57-2577
A43: 100029832 | B43: Peralta, Mayra L. | C43: Active | D43: Cashier, Concessions | E43: 605-86-7051
A44: 100053192 | B44: PEREZ, NANCY | C44: Active | D44: Cashier, Concessions | E44: 625-23-0781
A45: 100077499 | B45: MACIAS BARJAS, MIGUEL | C45: Active | D45: Cashier, Concessions | E45: 615-45-4078
A46: 100087286 | B46: Cruz, Juilan | C46: Active | D46: Concession Stand Worker | E46: 680-64-4979
A47: 100093407 | B47: Davis, Dimmery | C47: Active | D47: Cashier, Concessions | E47: 620-53-4186
A48: 100067131 | B48: Zechar, Lanny | C48: Active | D48: Lead Bartender, Concess | E48: 562-19-9743
A49: 100077488 | B49: ZARATE, DAVID A. | C49: Active | D49: Cashier, Concessions | E49: 610-51-7839
A50: 100087276 | B50: ZARAGOZA, MARTHA | C50: Active | D50: Club Attendant | E50: 609-50-6974
A51: 100087255 | B51: Wright, Bree | C51: Active | D51: Cook 3 | E51: 626-84-4281
A52: 100077562 | B52: ABDULLAH-LEE, NOAH H. | C52: Active | D52: Concession Stand Worker | E52: 614-39-2240
A53: 100077524 | B53: AGUIRRE, ALICE | C53: Active | D53: Cashier, Concessions | E53: 611-49-7156
A54: 100077561 | B54: ALLEN, ANIYA | C54: Active | D54: Cashier, Concessions | E54: 615-31-0176
A55: 100082246 | B55: Allison, Kameron | C55: Active | D55: Concession Stand Worker | E55: 323-02-9689
A56: 100082258 | B56: Amaya, Alma | C56: Active | D56: Concession Stand Worker | E56: 618-50-8242
A57: 100087246 | B57: ANGEL, MELVIN | C57: Active | D57: Cook 3 | E57: 626-29-6117
A58: 100077548 | B58: SANCHEZ II, MARCIA A. | C58: Active | D58: Cashier, Concessions | E58: 756-79-5916
A59: 100087261 | B59: Sanchez, Jesus | C59: Active | D59: Concession Stand Worker | E59: 609-60-1320
... A146: 100087240 | B146: JONES, KIRSTEN | C146: Active | D146: Cashier, Concessions | E146: 407-59-6763
A147: 100094456 | B147: Reyes, Oliver | C147: Active | D147: Cashier, Concessions | E147: 609-42-5606
A148: 100093370 | B148: Hill-Armstrong, Jacquelyn | C148: Active | D148: Cashier, Concessions | E148: 555-43-9589
A149: 100052692 | B149: Harris, Christopher | C149: Active | D149: Cook 3 | E149: 237-25-6251
A150: 100077512 | B150: PERCINO, BRIAN M. | C150: Active | D150: Cashier, Concessions | E150: 625-43-5169
A151: 100052656 | B151: reidinger, Blake | C151: Active | D151: Bartender, Premium | E151: 145-04-9005
A152: 100087251 | B152: ROJAS-ROMERO, STACEY | C152: Active | D152: Cashier, Concessions | E152: 606-49-8233
A153: 100049981 | B153: QUERO, CHRISTOPHER | C153: Active | D153: Cashier, Concessions | E153: 614-90-7886
A154: 100089119 | B154: Cohn, Mark I. | C154: Active | D154: Barback, Premium | E154: 261-08-7197
A155: 100089115 | B155: Cifuentes, Genesis | C155: Active | D155: Barback, Premium | E155: 621-70-4186

Sheet 11.27.22

Sheet 12.04.22

Sheet 12.08.22

Sheet 12.11.22

Sheet 12.17.22

Sheet 12.18.22

Sheet 12.25.22

Sheet Terminated
A1: Company | B1: Employee Name (Last Suffix, First MI) | C1: Employee Number | D1: Employment Status | E1: Status As Of | F1: Employee Email | G1: Last Hire | H1: Job Start | I1: Location | J1: Job Code | K1: Job

Sheet New Hire
A1: Employee Name (Last Suffix, First MI) | B1: Employee Number | C1: Birth Date | D1: Start Date (History) | E1: Job | F1: Address Line 1 + Address Line 2 | G1: City, State Zip Code (Formatted) | H1: Gender | I1: SSN (Formatted)
